{"021020": {"Estados Unidos": {"exp": 9859204.0, "imp": 0}}, "020629": {"Ecuador": {"exp": 141837.0, "imp": 0}, "Malasia": {"exp": 206478.0, "imp": 0}, "España": {"exp": 527060.0, "imp": 0}, "Congo": {"exp": 2847883.0, "imp": 0}, "French Polynesia": {"exp": 117759.0, "imp": 0}, "Aruba": {"exp": 44823.0, "imp": 0}, "Israel": {"exp": 5424266.0, "imp": 0}, "Estados Unidos": {"exp": 102056.0, "imp": 478066.0}, "Perú": {"exp": 6096440.0, "imp": 0}, "Países Bajos": {"exp": 2044628.0, "imp": 0}, "Curazao": {"exp": 704444.0, "imp": 0}, "Portugal": {"exp": 65503.0, "imp": 0}, "Argentina": {"exp": 116111.0, "imp": 0}, "China": {"exp": 930736296.0, "imp": 0}, "Tailandia": {"exp": 7242791.0, "imp": 0}, "Vietnam": {"exp": 152183.0, "imp": 0}, "Hong Kong": {"exp": 12800851.0, "imp": 0}, "Singapur": {"exp": 1280718.0, "imp": 0}, "Colombia": {"exp": 1656165.0, "imp": 0}, "Alemania": {"exp": 243290.0, "imp": 0}, "Rusia": {"exp": 27158278.0, "imp": 0}, "Costa de Marfil": {"exp": 814522.0, "imp": 0}, "Brasil": {"exp": 506381.0, "imp": 291242.0}, "Sudáfrica": {"exp": 228070.0, "imp": 0}, "Afganistán": {"exp": 36056.0, "imp": 0}, "Hungría": {"exp": 21905.0, "imp": 0}, "Ghana": {"exp": 518827.0, "imp": 0}, "Liberia": {"exp": 32296.0, "imp": 0}, "Corea del Sur": {"exp": 255351.0, "imp": 0}, "Kuwait": {"exp": 167647.0, "imp": 0}, "Arabia Saudita": {"exp": 10055.0, "imp": 0}, "Albania": {"exp": 114910.0, "imp": 0}, "Georgia": {"exp": 187996.0, "imp": 0}, "Sierra Leona": {"exp": 64759.0, "imp": 0}, "Reino Unido": {"exp": 78024.0, "imp": 0}, "Rep. Dem. del Congo": {"exp": 94500.0, "imp": 0}, "Gabón": {"exp": 136809.0, "imp": 0}, "Angola": {"exp": 133939.0, "imp": 0}, "Emiratos Árabes": {"exp": 7132.0, "imp": 0}, "Egipto": {"exp": 935222.0, "imp": 0}, "Jordania": {"exp": 5135.0, "imp": 0}, "Suiza": {"exp": 14159.0, "imp": 0}, "Paraguay": {"exp": 0, "imp": 542080.0}}, "020714": {"Hong Kong": {"exp": 325230.0, "imp": 0}, "Brasil": {"exp": 28918.0, "imp": 5445478.0}, "Argentina": {"exp": 2652645.0, "imp": 1275630.0}, "Congo": {"exp": 18444.0, "imp": 0}, "Guinea": {"exp": 48157.0, "imp": 0}, "Macao": {"exp": 163688.0, "imp": 0}, "Cuba": {"exp": 46151.0, "imp": 0}, "Benin": {"exp": 39573.0, "imp": 0}, "Gabón": {"exp": 58629.0, "imp": 0}, "Namibia": {"exp": 46860.0, "imp": 0}, "Estados Unidos": {"exp": 0, "imp": 188391.0}, "Chile": {"exp": 0, "imp": 1210739.0}}, "020810": {"Bélgica": {"exp": 3109490.0, "imp": 0}, "Italia": {"exp": 1183.0, "imp": 0}}, "020442": {"French Polynesia": {"exp": 1015606.0, "imp": 0}, "Brasil": {"exp": 149867502.0, "imp": 0}, "Kuwait": {"exp": 2727528.0, "imp": 0}, "Seychelles": {"exp": 137104.0, "imp": 0}, "Baréin": {"exp": 383053.0, "imp": 0}, "Túnez": {"exp": 27389.0, "imp": 0}, "China": {"exp": 90293015.0, "imp": 0}, "Omán": {"exp": 1038412.0, "imp": 0}, "Estados Unidos": {"exp": 665641.0, "imp": 0}, "Jordania": {"exp": 434727.0, "imp": 0}, "Rusia": {"exp": 4982315.0, "imp": 0}, "Ecuador": {"exp": 987554.0, "imp": 0}, "Hong Kong": {"exp": 116998.0, "imp": 0}, "Emiratos Árabes": {"exp": 3030062.0, "imp": 0}, "Mauricio": {"exp": 337472.0, "imp": 0}, "Arabia Saudita": {"exp": 2418244.0, "imp": 0}, "Albania": {"exp": 140367.0, "imp": 0}, "Alemania": {"exp": 144659.0, "imp": 0}, "Trinidad y Tobago": {"exp": 296485.0, "imp": 0}, "Qatar": {"exp": 1270771.0, "imp": 0}, "Angola": {"exp": 306503.0, "imp": 0}, "Turquía": {"exp": 174151.0, "imp": 0}, "Líbano": {"exp": 302829.0, "imp": 0}, "Libia": {"exp": 143780.0, "imp": 0}, "Argentina": {"exp": 36340.0, "imp": 0}, "Panamá": {"exp": 6444.0, "imp": 0}, "Irak": {"exp": 737414.0, "imp": 0}, "Israel": {"exp": 1372360.0, "imp": 0}}, "020712": {"Baréin": {"exp": 1084141.0, "imp": 0}, "Angola": {"exp": 1708318.0, "imp": 0}, "Qatar": {"exp": 3954697.0, "imp": 0}, "Omán": {"exp": 750139.0, "imp": 0}, "Congo": {"exp": 1177222.0, "imp": 0}, "Hong Kong": {"exp": 39748.0, "imp": 0}, "Afganistán": {"exp": 175535.0, "imp": 0}, "Guinea Ecuatorial": {"exp": 22360.0, "imp": 0}, "Yemen": {"exp": 137481.0, "imp": 0}, "Emiratos Árabes": {"exp": 516747.0, "imp": 0}, "Tajikistan": {"exp": 56936.0, "imp": 0}, "Liberia": {"exp": 43765.0, "imp": 0}, "Ghana": {"exp": 56771.0, "imp": 0}, "Benin": {"exp": 70118.0, "imp": 0}, "Camerún": {"exp": 40460.0, "imp": 0}, "Central African Rep.": {"exp": 20230.0, "imp": 0}, "Brasil": {"exp": 0, "imp": 43448.0}, "Argentina": {"exp": 0, "imp": 1326871.0}}, "020210": {"China": {"exp": 1120898.0, "imp": 0}}, "020130": {"China": {"exp": 34346610.0, "imp": 0}, "Colombia": {"exp": 5203242.0, "imp": 0}, "Italia": {"exp": 119794982.0, "imp": 0}, "Perú": {"exp": 466839.0, "imp": 0}, "Portugal": {"exp": 35740062.0, "imp": 0}, "Emiratos Árabes": {"exp": 1024280.0, "imp": 0}, "Dinamarca": {"exp": 38745585.0, "imp": 0}, "Países Bajos": {"exp": 974267691.0, "imp": 0}, "Rusia": {"exp": 18694343.0, "imp": 0}, "Noruega": {"exp": 1952331.0, "imp": 0}, "Argentina": {"exp": 2673.0, "imp": 4257090.0}, "Francia": {"exp": 5064926.0, "imp": 0}, "Ecuador": {"exp": 149165.0, "imp": 0}, "Suiza": {"exp": 125356452.0, "imp": 0}, "Estados Unidos": {"exp": 239967733.0, "imp": 0}, "Kuwait": {"exp": 426390.0, "imp": 0}, "Qatar": {"exp": 990510.0, "imp": 0}, "Chile": {"exp": 207213266.0, "imp": 0}, "Reino Unido": {"exp": 130951861.0, "imp": 0}, "Brasil": {"exp": 116468056.0, "imp": 141858865.0}, "Canadá": {"exp": 3085736.0, "imp": 0}, "Hong Kong": {"exp": 904259.0, "imp": 0}, "México": {"exp": 1749377.0, "imp": 0}, "España": {"exp": 135174756.0, "imp": 0}, "Suecia": {"exp": 18008661.0, "imp": 0}, "Alemania": {"exp": 253574579.0, "imp": 0}, "Singapur": {"exp": 2608653.0, "imp": 0}, "Líbano": {"exp": 1665327.0, "imp": 0}, "Sudáfrica": {"exp": 507.0, "imp": 0}, "Arabia Saudita": {"exp": 669298.0, "imp": 0}, "Vietnam": {"exp": 1416.0, "imp": 0}, "Bélgica": {"exp": 3100477.0, "imp": 0}, "Japón": {"exp": 121145999.0, "imp": 0}, "Israel": {"exp": 54836293.0, "imp": 0}, "Paraguay": {"exp": 117929.0, "imp": 19070679.0}, "Omán": {"exp": 118107.0, "imp": 0}, "Corea del Sur": {"exp": 227462.0, "imp": 0}, "Malasia": {"exp": 1539.0, "imp": 0}, "El Salvador": {"exp": 1360.0, "imp": 0}, "Grecia": {"exp": 380.0, "imp": 0}, "Seychelles": {"exp": 5745.0, "imp": 0}}, "020443": {"Ecuador": {"exp": 9361.0, "imp": 0}, "Estados Unidos": {"exp": 1825369.0, "imp": 0}, "Israel": {"exp": 497678.0, "imp": 0}, "Brasil": {"exp": 22204506.0, "imp": 0}, "Rusia": {"exp": 1004740.0, "imp": 0}, "French Polynesia": {"exp": 514083.0, "imp": 0}, "Finlandia": {"exp": 415023.0, "imp": 0}, "España": {"exp": 317835.0, "imp": 0}, "Noruega": {"exp": 1368532.0, "imp": 0}, "Canadá": {"exp": 23774170.0, "imp": 0}, "China": {"exp": 9287227.0, "imp": 0}, "Países Bajos": {"exp": 11188790.0, "imp": 0}, "Francia": {"exp": 2180457.0, "imp": 0}, "Reino Unido": {"exp": 1523013.0, "imp": 0}, "Bélgica": {"exp": 762744.0, "imp": 0}, "Hong Kong": {"exp": 44070.0, "imp": 0}, "Alemania": {"exp": 2575189.0, "imp": 0}, "Seychelles": {"exp": 27011.0, "imp": 0}, "Dinamarca": {"exp": 1016969.0, "imp": 0}, "Suiza": {"exp": 2727392.0, "imp": 0}, "Mauricio": {"exp": 45529.0, "imp": 0}, "Emiratos Árabes": {"exp": 1393461.0, "imp": 0}, "Kuwait": {"exp": 252368.0, "imp": 0}, "Arabia Saudita": {"exp": 245452.0, "imp": 0}, "Baréin": {"exp": 8525.0, "imp": 0}, "Jordania": {"exp": 24657.0, "imp": 0}, "Turquía": {"exp": 101883.0, "imp": 0}, "Trinidad y Tobago": {"exp": 3777.0, "imp": 0}, "Omán": {"exp": 64355.0, "imp": 0}, "Líbano": {"exp": 116600.0, "imp": 0}, "Panamá": {"exp": 9393.0, "imp": 0}, "Irak": {"exp": 14970.0, "imp": 0}, "Portugal": {"exp": 115095.0, "imp": 0}}, "020430": {"Kuwait": {"exp": 2132289.0, "imp": 0}, "Hong Kong": {"exp": 1043111.0, "imp": 0}, "Jordania": {"exp": 5601314.0, "imp": 0}, "Brasil": {"exp": 340879.0, "imp": 0}, "Baréin": {"exp": 956352.0, "imp": 0}, "Túnez": {"exp": 63383.0, "imp": 0}, "China": {"exp": 152961055.0, "imp": 0}, "Malasia": {"exp": 209839.0, "imp": 0}, "Estados Unidos": {"exp": 4184226.0, "imp": 0}, "Emiratos Árabes": {"exp": 5214369.0, "imp": 0}, "Omán": {"exp": 1525364.0, "imp": 0}, "Arabia Saudita": {"exp": 1290729.0, "imp": 0}, "Egipto": {"exp": 917072.0, "imp": 0}, "American Samoa": {"exp": 71471.0, "imp": 0}, "Turquía": {"exp": 27936.0, "imp": 0}, "Líbano": {"exp": 38155.0, "imp": 0}, "Libia": {"exp": 1683061.0, "imp": 0}, "Ecuador": {"exp": 617.0, "imp": 0}, "Panamá": {"exp": 11708.0, "imp": 0}, "Irak": {"exp": 486387.0, "imp": 0}, "Qatar": {"exp": 331913.0, "imp": 0}, "Rusia": {"exp": 254302.0, "imp": 0}}, "020120": {"Brasil": {"exp": 12554114.0, "imp": 0}, "China": {"exp": 300.0, "imp": 0}, "Emiratos Árabes": {"exp": 18502.0, "imp": 0}, "Singapur": {"exp": 1298.0, "imp": 0}, "Israel": {"exp": 2.0, "imp": 0}, "Argentina": {"exp": 0, "imp": 677072.0}}, "020230": {"Rusia": {"exp": 104665888.0, "imp": 0}, "Portugal": {"exp": 43748377.0, "imp": 0}, "Kuwait": {"exp": 10361440.0, "imp": 0}, "Jordania": {"exp": 223485.0, "imp": 0}, "Chile": {"exp": 9513092.0, "imp": 0}, "Barbados": {"exp": 26800325.0, "imp": 0}, "Brasil": {"exp": 275039889.0, "imp": 3702499.0}, "Israel": {"exp": 433234591.0, "imp": 0}, "Hong Kong": {"exp": 3821730.0, "imp": 0}, "Canadá": {"exp": 315795136.0, "imp": 0}, "China": {"exp": 5495278644.0, "imp": 0}, "Reino Unido": {"exp": 45050195.0, "imp": 0}, "Qatar": {"exp": 132157.0, "imp": 0}, "España": {"exp": 65477120.0, "imp": 0}, "Bélgica": {"exp": 1699756.0, "imp": 0}, "México": {"exp": 6093195.0, "imp": 0}, "Senegal": {"exp": 526466.0, "imp": 0}, "Italia": {"exp": 192178785.0, "imp": 0}, "Chipre": {"exp": 1078384.0, "imp": 0}, "Dinamarca": {"exp": 18127441.0, "imp": 0}, "Trinidad y Tobago": {"exp": 103549259.0, "imp": 0}, "Alemania": {"exp": 51536972.0, "imp": 0}, "Finlandia": {"exp": 7906300.0, "imp": 0}, "Panamá": {"exp": 6306219.0, "imp": 0}, "Ucrania": {"exp": 154754.0, "imp": 0}, "Suiza": {"exp": 751262.0, "imp": 0}, "Ecuador": {"exp": 12659258.0, "imp": 0}, "Dem. People's Rep. of Korea": {"exp": 107586.0, "imp": 0}, "French Polynesia": {"exp": 68233302.0, "imp": 0}, "Países Bajos": {"exp": 195744765.0, "imp": 0}, "Vietnam": {"exp": 361740.0, "imp": 0}, "Singapur": {"exp": 658514.0, "imp": 0}, "Camboya": {"exp": 455.0, "imp": 0}, "Perú": {"exp": 16168182.0, "imp": 0}, "Antigua y Barbuda": {"exp": 104398.0, "imp": 0}, "Suecia": {"exp": 11370638.0, "imp": 0}, "Estados Unidos": {"exp": 1909183743.0, "imp": 0}, "Noruega": {"exp": 60165590.0, "imp": 0}, "Emiratos Árabes": {"exp": 2224643.0, "imp": 0}, "Sudáfrica": {"exp": 5878351.0, "imp": 0}, "Francia": {"exp": 19268544.0, "imp": 0}, "Corea del Sur": {"exp": 38126821.0, "imp": 0}, "Colombia": {"exp": 2654835.0, "imp": 0}, "Arabia Saudita": {"exp": 6776403.0, "imp": 0}, "Afganistán": {"exp": 2673.0, "imp": 0}, "Túnez": {"exp": 95614.0, "imp": 0}, "Costa de Marfil": {"exp": 14136.0, "imp": 0}, "Aruba": {"exp": 171809.0, "imp": 0}, "Japón": {"exp": 86848614.0, "imp": 0}, "Papua New Guinea": {"exp": 223826.0, "imp": 0}, "Namibia": {"exp": 115887.0, "imp": 0}, "Líbano": {"exp": 1613711.0, "imp": 0}, "Guinea Ecuatorial": {"exp": 87779.0, "imp": 0}, "Liberia": {"exp": 24718.0, "imp": 0}, "Egipto": {"exp": 2160057.0, "imp": 0}, "Estado de Palestina": {"exp": 4414179.0, "imp": 0}, "Curazao": {"exp": 71856.0, "imp": 0}, "Venezuela": {"exp": 103838.0, "imp": 0}, "Argentina": {"exp": 7287852.0, "imp": 475597.0}, "Cuba": {"exp": 6039.0, "imp": 0}, "Nueva Zelanda": {"exp": 1013.0, "imp": 0}, "Lituania": {"exp": 143438.0, "imp": 0}, "El Salvador": {"exp": 5684.0, "imp": 0}, "Baréin": {"exp": 253546.0, "imp": 0}, "Angola": {"exp": 414498.0, "imp": 0}, "Turquía": {"exp": 116183.0, "imp": 0}, "Tailandia": {"exp": 168345.0, "imp": 0}, "Omán": {"exp": 98248.0, "imp": 0}, "Macedonia del Norte": {"exp": 168097.0, "imp": 0}, "Kazajistán": {"exp": 889881.0, "imp": 0}, "Cabo Verde": {"exp": 208493.0, "imp": 0}, "Albania": {"exp": 142376.0, "imp": 0}, "Paraguay": {"exp": 0, "imp": 7235361.0}}, "020441": {"Baréin": {"exp": 1989207.0, "imp": 0}, "Omán": {"exp": 7713807.0, "imp": 0}, "Túnez": {"exp": 78264.0, "imp": 0}, "Brasil": {"exp": 208780.0, "imp": 0}, "Emiratos Árabes": {"exp": 336740.0, "imp": 0}, "Estados Unidos": {"exp": 6101236.0, "imp": 0}, "China": {"exp": 39757054.0, "imp": 0}, "Ecuador": {"exp": 39285.0, "imp": 0}, "Kuwait": {"exp": 954122.0, "imp": 0}, "Qatar": {"exp": 451686.0, "imp": 0}, "Rusia": {"exp": 105169.0, "imp": 0}, "Arabia Saudita": {"exp": 18845.0, "imp": 0}, "Trinidad y Tobago": {"exp": 572316.0, "imp": 0}, "Guyana": {"exp": 140008.0, "imp": 0}, "Irak": {"exp": 387650.0, "imp": 0}, "Jordania": {"exp": 149729.0, "imp": 0}, "Corea del Sur": {"exp": 57582.0, "imp": 0}, "Libia": {"exp": 52407.0, "imp": 0}}, "020690": {"Hong Kong": {"exp": 3195066.0, "imp": 0}, "Rusia": {"exp": 1131989.0, "imp": 0}, "Brasil": {"exp": 163699.0, "imp": 0}, "China": {"exp": 4654949.0, "imp": 0}, "Polonia": {"exp": 281511.0, "imp": 0}, "Bélgica": {"exp": 210783.0, "imp": 0}, "Kazajistán": {"exp": 1683085.0, "imp": 0}, "Japón": {"exp": 2510044.0, "imp": 0}, "Costa de Marfil": {"exp": 43800.0, "imp": 0}, "Alemania": {"exp": 479227.0, "imp": 0}, "Vietnam": {"exp": 3782108.0, "imp": 0}, "Francia": {"exp": 75978.0, "imp": 0}, "French Polynesia": {"exp": 1543.0, "imp": 0}, "Emiratos Árabes": {"exp": 377665.0, "imp": 0}, "Tailandia": {"exp": 138703.0, "imp": 0}, "Mauricio": {"exp": 12652.0, "imp": 0}, "Kuwait": {"exp": 143998.0, "imp": 0}, "Baréin": {"exp": 842.0, "imp": 0}, "Países Bajos": {"exp": 25206.0, "imp": 0}, "Ecuador": {"exp": 7369.0, "imp": 0}, "Jordania": {"exp": 52595.0, "imp": 0}, "Líbano": {"exp": 76889.0, "imp": 0}, "Guyana": {"exp": 2228.0, "imp": 0}, "Israel": {"exp": 13158.0, "imp": 0}}, "020220": {"China": {"exp": 1561495913.0, "imp": 0}, "Hong Kong": {"exp": 368100.0, "imp": 0}, "Ecuador": {"exp": 1110176.0, "imp": 0}, "Brasil": {"exp": 13396004.0, "imp": 609151.0}, "Trinidad y Tobago": {"exp": 72804.0, "imp": 0}, "Qatar": {"exp": 158.0, "imp": 0}, "French Polynesia": {"exp": 4650.0, "imp": 0}, "Senegal": {"exp": 4464.0, "imp": 0}, "Canadá": {"exp": 67296.0, "imp": 0}, "Estados Unidos": {"exp": 229407.0, "imp": 0}, "Arabia Saudita": {"exp": 128980.0, "imp": 0}, "Corea del Sur": {"exp": 192459.0, "imp": 0}, "Kuwait": {"exp": 235305.0, "imp": 0}, "Aruba": {"exp": 34507.0, "imp": 0}, "Cuba": {"exp": 1278.0, "imp": 0}, "Sudáfrica": {"exp": 117190.0, "imp": 0}, "Egipto": {"exp": 68965.0, "imp": 0}, "Angola": {"exp": 209266.0, "imp": 0}, "Baréin": {"exp": 196912.0, "imp": 0}, "Emiratos Árabes": {"exp": 8642.0, "imp": 0}, "Israel": {"exp": 6342994.0, "imp": 0}, "Japón": {"exp": 87606.0, "imp": 0}, "Argentina": {"exp": 0, "imp": 2661832.0}}, "020500": {"Bielorrusia": {"exp": 185211.0, "imp": 0}, "Bélgica": {"exp": 68848422.0, "imp": 0}, "Japón": {"exp": 22426866.0, "imp": 0}, "Países Bajos": {"exp": 142997.0, "imp": 0}, "Suiza": {"exp": 238319.0, "imp": 0}, "Francia": {"exp": 64363613.0, "imp": 0}, "Kazajistán": {"exp": 11610944.0, "imp": 0}, "Rusia": {"exp": 21161075.0, "imp": 0}, "Vietnam": {"exp": 2817785.0, "imp": 0}, "Alemania": {"exp": 6912466.0, "imp": 0}, "Polonia": {"exp": 1077012.0, "imp": 0}, "Tailandia": {"exp": 475971.0, "imp": 0}, "Hong Kong": {"exp": 1933053.0, "imp": 0}, "España": {"exp": 992284.0, "imp": 0}, "Italia": {"exp": 688826.0, "imp": 0}, "China": {"exp": 3641035.0, "imp": 0}}, "020621": {"Rusia": {"exp": 33022197.0, "imp": 0}, "Hong Kong": {"exp": 4975544.0, "imp": 0}, "Singapur": {"exp": 4868.0, "imp": 0}, "French Polynesia": {"exp": 29943.0, "imp": 0}, "Israel": {"exp": 2997907.0, "imp": 0}, "China": {"exp": 6884418.0, "imp": 0}, "Alemania": {"exp": 20611.0, "imp": 0}, "Argentina": {"exp": 5.0, "imp": 0}, "Corea del Sur": {"exp": 61.0, "imp": 0}, "Colombia": {"exp": 679177.0, "imp": 0}, "Japón": {"exp": 28234929.0, "imp": 0}, "Tailandia": {"exp": 60366.0, "imp": 0}, "Brasil": {"exp": 0, "imp": 1724323.0}, "Paraguay": {"exp": 0, "imp": 389269.0}}, "020622": {"China": {"exp": 837265.0, "imp": 0}, "Colombia": {"exp": 1302741.0, "imp": 0}, "Rusia": {"exp": 45478802.0, "imp": 0}, "Países Bajos": {"exp": 6302.0, "imp": 0}, "Brasil": {"exp": 5695223.0, "imp": 80873.0}, "Argentina": {"exp": 5.0, "imp": 0}, "Kuwait": {"exp": 254543.0, "imp": 0}, "Kazajistán": {"exp": 52173.0, "imp": 0}, "Egipto": {"exp": 6960791.0, "imp": 0}, "Estado de Palestina": {"exp": 33405.0, "imp": 0}, "Costa de Marfil": {"exp": 61139.0, "imp": 0}, "Gambia": {"exp": 23841.0, "imp": 0}, "Emiratos Árabes": {"exp": 23906.0, "imp": 0}, "Arabia Saudita": {"exp": 108314.0, "imp": 0}, "Ecuador": {"exp": 334498.0, "imp": 0}, "Paraguay": {"exp": 0, "imp": 77697.0}}, "021012": {"Reino Unido": {"exp": 1110.0, "imp": 0}}, "020421": {"Brasil": {"exp": 156777.0, "imp": 0}}, "021019": {"España": {"exp": 85166.0, "imp": 1557483.0}, "Paraguay": {"exp": 26373.0, "imp": 0}, "Reino Unido": {"exp": 5734.0, "imp": 0}, "Italia": {"exp": 0, "imp": 119958.0}, "Brasil": {"exp": 0, "imp": 269173.0}}, "020423": {"Suiza": {"exp": 377.0, "imp": 0}, "Emiratos Árabes": {"exp": 117647.0, "imp": 0}, "Arabia Saudita": {"exp": 2.0, "imp": 0}, "Malasia": {"exp": 630.0, "imp": 0}}, "020649": {"Brasil": {"exp": 48890.0, "imp": 403675.0}, "Paraguay": {"exp": 0, "imp": 360277.0}, "España": {"exp": 0, "imp": 97630.0}, "Argentina": {"exp": 0, "imp": 14028.0}, "Chile": {"exp": 0, "imp": 16636.0}}, "020610": {"Japón": {"exp": 5677.0, "imp": 0}, "Argentina": {"exp": 0, "imp": 806.0}, "Brasil": {"exp": 0, "imp": 54272.0}}, "020410": {"Baréin": {"exp": 292.0, "imp": 0}}, "020680": {"Japón": {"exp": 36435.0, "imp": 0}}, "020422": {"Arabia Saudita": {"exp": 1.0, "imp": 0}, "Emiratos Árabes": {"exp": 257803.0, "imp": 0}}, "020910": {"España": {"exp": 0, "imp": 2419690.0}, "Finlandia": {"exp": 0, "imp": 43043.0}, "Chile": {"exp": 0, "imp": 1795910.0}, "Paraguay": {"exp": 0, "imp": 1633167.0}, "Brasil": {"exp": 0, "imp": 920086.0}, "Bélgica": {"exp": 0, "imp": 1020601.0}, "Argentina": {"exp": 0, "imp": 250264.0}, "Dinamarca": {"exp": 0, "imp": 53122.0}}, "020319": {"Brasil": {"exp": 0, "imp": 4388773.0}}, "020329": {"Brasil": {"exp": 0, "imp": 114166423.0}, "Dinamarca": {"exp": 0, "imp": 252165.0}, "Paraguay": {"exp": 0, "imp": 2557309.0}, "España": {"exp": 0, "imp": 1001362.0}, "Argentina": {"exp": 0, "imp": 1523490.0}, "Chile": {"exp": 0, "imp": 53536.0}}, "020725": {"Brasil": {"exp": 0, "imp": 850.0}}, "021011": {"España": {"exp": 0, "imp": 75323.0}}, "020745": {"Francia": {"exp": 0, "imp": 61288.0}}}