{"040221": {"Países Bajos": {"exp": 1579750.0, "imp": 0}, "Estados Unidos": {"exp": 182591.0, "imp": 0}, "Omán": {"exp": 3547025.0, "imp": 0}, "Paraguay": {"exp": 1621089.0, "imp": 0}, "Sudáfrica": {"exp": 26270550.0, "imp": 0}, "China": {"exp": 373013257.0, "imp": 0}, "Mauritania": {"exp": 24696209.0, "imp": 0}, "Rusia": {"exp": 79674252.0, "imp": 0}, "Chile": {"exp": 43668829.0, "imp": 0}, "Bolivia": {"exp": 5286785.0, "imp": 0}, "Argelia": {"exp": 1218541794.0, "imp": 0}, "Nigeria": {"exp": 42939065.0, "imp": 0}, "Brunei Darussalam": {"exp": 606167.0, "imp": 0}, "Mali": {"exp": 3776413.0, "imp": 0}, "Filipinas": {"exp": 1893640.0, "imp": 0}, "Singapur": {"exp": 36624324.0, "imp": 0}, "Costa de Marfil": {"exp": 9734077.0, "imp": 0}, "Emiratos Árabes": {"exp": 32766958.0, "imp": 0}, "Egipto": {"exp": 56618737.0, "imp": 0}, "Tailandia": {"exp": 722107.0, "imp": 0}, "Brasil": {"exp": 997910246.0, "imp": 0}, "Zambia": {"exp": 2083158.0, "imp": 0}, "Camerún": {"exp": 6840853.0, "imp": 0}, "Venezuela": {"exp": 24904979.0, "imp": 0}, "Colombia": {"exp": 35250880.0, "imp": 0}, "Panamá": {"exp": 30218138.0, "imp": 0}, "Arabia Saudita": {"exp": 13940812.0, "imp": 0}, "Argentina": {"exp": 7680028.0, "imp": 0}, "Bangladesh": {"exp": 7739832.0, "imp": 0}, "México": {"exp": 35946844.0, "imp": 0}, "Malasia": {"exp": 5925315.0, "imp": 0}, "Cuba": {"exp": 144718432.0, "imp": 0}, "Trinidad y Tobago": {"exp": 1432132.0, "imp": 0}, "Yemen": {"exp": 973360.0, "imp": 0}, "Francia": {"exp": 79386.0, "imp": 0}, "Irak": {"exp": 1065549.0, "imp": 0}, "Senegal": {"exp": 5926220.0, "imp": 0}, "Central African Rep.": {"exp": 84208.0, "imp": 0}, "Myanmar": {"exp": 53442.0, "imp": 0}, "Nepal": {"exp": 810751.0, "imp": 0}, "Jordania": {"exp": 2312648.0, "imp": 0}, "Canadá": {"exp": 70350.0, "imp": 0}, "Sri Lanka": {"exp": 89434.0, "imp": 0}, "Perú": {"exp": 2364886.0, "imp": 0}, "Vietnam": {"exp": 6957217.0, "imp": 0}, "Túnez": {"exp": 81875.0, "imp": 0}, "Siria": {"exp": 1399741.0, "imp": 0}, "Japón": {"exp": 143.0, "imp": 0}, "Mauricio": {"exp": 9575291.0, "imp": 0}, "Mongolia": {"exp": 1000091.0, "imp": 0}, "Pakistán": {"exp": 1228046.0, "imp": 0}, "Libia": {"exp": 5674612.0, "imp": 0}, "Burkina Faso": {"exp": 2289849.0, "imp": 0}, "Níger": {"exp": 3964.0, "imp": 0}, "Kuwait": {"exp": 433110.0, "imp": 0}, "Gabón": {"exp": 2154957.0, "imp": 0}, "Suriname": {"exp": 1677445.0, "imp": 0}, "Ghana": {"exp": 4105860.0, "imp": 0}, "Angola": {"exp": 4355402.0, "imp": 0}, "Corea del Sur": {"exp": 171231.0, "imp": 0}, "Guinea": {"exp": 558289.0, "imp": 0}, "Gambia": {"exp": 898356.0, "imp": 0}, "Qatar": {"exp": 19751403.0, "imp": 0}, "Djibouti": {"exp": 91250.0, "imp": 0}, "Mozambique": {"exp": 209000.0, "imp": 0}, "Madagascar": {"exp": 1172251.0, "imp": 0}, "Congo": {"exp": 670177.0, "imp": 0}, "Cabo Verde": {"exp": 743744.0, "imp": 0}, "Benin": {"exp": 452786.0, "imp": 0}, "Guyana": {"exp": 268262.0, "imp": 0}, "Kazajistán": {"exp": 1548255.0, "imp": 0}, "Guinea-Bissau": {"exp": 106598.0, "imp": 0}, "India": {"exp": 21.0, "imp": 0}, "Turquía": {"exp": 102658.0, "imp": 0}, "Georgia": {"exp": 1937139.0, "imp": 0}, "El Salvador": {"exp": 283229.0, "imp": 0}, "Líbano": {"exp": 4765759.0, "imp": 0}, "Uzbekistán": {"exp": 100.0, "imp": 0}, "Sao Tome and Principe": {"exp": 45938.0, "imp": 0}, "Grenada": {"exp": 95000.0, "imp": 0}, "Seychelles": {"exp": 43399.0, "imp": 0}, "Alemania": {"exp": 0, "imp": 1334.0}}, "040110": {"Chile": {"exp": 7096.0, "imp": 0}, "Argentina": {"exp": 764707.0, "imp": 135293.0}, "Trinidad y Tobago": {"exp": 20291.0, "imp": 0}, "Brasil": {"exp": 12855.0, "imp": 590631.0}, "China": {"exp": 181859.0, "imp": 0}, "Brunei Darussalam": {"exp": 23.0, "imp": 0}, "Francia": {"exp": 3.0, "imp": 2808.0}, "Reino Unido": {"exp": 659.0, "imp": 0}, "Venezuela": {"exp": 40.0, "imp": 0}, "Alemania": {"exp": 0, "imp": 626.0}, "Países Bajos": {"exp": 0, "imp": 2901.0}}, "040150": {"Paraguay": {"exp": 200760.0, "imp": 0}, "Cuba": {"exp": 18.0, "imp": 0}, "Argentina": {"exp": 6522553.0, "imp": 87318.0}}, "040510": {"Argentina": {"exp": 5683464.0, "imp": 1329632.0}, "Egipto": {"exp": 29770452.0, "imp": 0}, "Hong Kong": {"exp": 788861.0, "imp": 0}, "México": {"exp": 1003747.0, "imp": 0}, "Vietnam": {"exp": 1253165.0, "imp": 0}, "Georgia": {"exp": 20749273.0, "imp": 0}, "China": {"exp": 6322399.0, "imp": 0}, "Costa de Marfil": {"exp": 519055.0, "imp": 0}, "Brasil": {"exp": 26537130.0, "imp": 1438280.0}, "Emiratos Árabes": {"exp": 7782330.0, "imp": 0}, "Rusia": {"exp": 176496343.0, "imp": 0}, "Turquía": {"exp": 8531222.0, "imp": 0}, "Túnez": {"exp": 4754009.0, "imp": 0}, "Marruecos": {"exp": 26574851.0, "imp": 0}, "Paraguay": {"exp": 31973.0, "imp": 0}, "Chile": {"exp": 8534133.0, "imp": 0}, "Malasia": {"exp": 4273392.0, "imp": 0}, "Sudáfrica": {"exp": 12385689.0, "imp": 0}, "Argelia": {"exp": 6213525.0, "imp": 0}, "Singapur": {"exp": 3015618.0, "imp": 0}, "Tailandia": {"exp": 5.0, "imp": 0}, "Estados Unidos": {"exp": 564471.0, "imp": 0}, "Panamá": {"exp": 210018.0, "imp": 0}, "Arabia Saudita": {"exp": 18163998.0, "imp": 0}, "Mauricio": {"exp": 5.0, "imp": 0}, "Perú": {"exp": 9790694.0, "imp": 0}, "Senegal": {"exp": 532244.0, "imp": 0}, "Irán": {"exp": 5318868.0, "imp": 0}, "Japón": {"exp": 153620.0, "imp": 0}, "Mongolia": {"exp": 38474.0, "imp": 0}, "Baréin": {"exp": 22841066.0, "imp": 0}, "Bolivia": {"exp": 394175.0, "imp": 0}, "Angola": {"exp": 24425.0, "imp": 0}, "Filipinas": {"exp": 259979.0, "imp": 0}, "Colombia": {"exp": 352993.0, "imp": 0}, "Omán": {"exp": 48.0, "imp": 0}, "Nigeria": {"exp": 435428.0, "imp": 0}, "Kazajistán": {"exp": 772500.0, "imp": 0}, "Kuwait": {"exp": 149209.0, "imp": 0}, "Benin": {"exp": 332476.0, "imp": 0}, "Cuba": {"exp": 812066.0, "imp": 0}, "Irak": {"exp": 228974.0, "imp": 0}, "Israel": {"exp": 3056162.0, "imp": 0}, "Jordania": {"exp": 229000.0, "imp": 0}, "Bangladesh": {"exp": 66500.0, "imp": 0}, "Armenia": {"exp": 123810.0, "imp": 0}, "Yemen": {"exp": 107500.0, "imp": 0}, "Líbano": {"exp": 151350.0, "imp": 0}, "Libia": {"exp": 1224553.0, "imp": 0}, "Brunei Darussalam": {"exp": 48019.0, "imp": 0}, "Francia": {"exp": 0, "imp": 148.0}}, "040900": {"Polonia": {"exp": 2517466.0, "imp": 0}, "Portugal": {"exp": 925574.0, "imp": 0}, "Estados Unidos": {"exp": 97459398.0, "imp": 0}, "Italia": {"exp": 2394376.0, "imp": 0}, "Chequia": {"exp": 2850881.0, "imp": 0}, "Suiza": {"exp": 1010142.0, "imp": 0}, "España": {"exp": 37970547.0, "imp": 0}, "Alemania": {"exp": 15954583.0, "imp": 0}, "Brasil": {"exp": 68561.0, "imp": 0}, "Francia": {"exp": 1777457.0, "imp": 1452.0}, "Reino Unido": {"exp": 1631181.0, "imp": 0}, "Irlanda": {"exp": 547752.0, "imp": 0}, "Países Bajos": {"exp": 777696.0, "imp": 0}, "Austria": {"exp": 4653754.0, "imp": 0}, "Bélgica": {"exp": 1965205.0, "imp": 0}, "Israel": {"exp": 773440.0, "imp": 0}, "Sudáfrica": {"exp": 1064474.0, "imp": 0}, "Dinamarca": {"exp": 1753181.0, "imp": 0}, "China": {"exp": 24.0, "imp": 0}, "Eslovenia": {"exp": 73248.0, "imp": 0}, "Eslovaquia": {"exp": 386274.0, "imp": 0}, "Emiratos Árabes": {"exp": 126940.0, "imp": 0}, "Australia": {"exp": 90574.0, "imp": 0}, "Arabia Saudita": {"exp": 64555.0, "imp": 0}}, "040590": {"Líbano": {"exp": 104727.0, "imp": 0}, "Brasil": {"exp": 5456596.0, "imp": 0}, "México": {"exp": 1501441.0, "imp": 0}, "Costa Rica": {"exp": 607088.0, "imp": 0}, "Francia": {"exp": 70267.0, "imp": 0}, "Rep. Dominicana": {"exp": 200.0, "imp": 0}, "Guyana": {"exp": 282925.0, "imp": 0}, "Jamaica": {"exp": 31853.0, "imp": 0}, "Malasia": {"exp": 234462.0, "imp": 0}, "Mongolia": {"exp": 10.0, "imp": 0}, "Emiratos Árabes": {"exp": 5.0, "imp": 0}, "Argelia": {"exp": 1953003.0, "imp": 0}, "Arabia Saudita": {"exp": 5190417.0, "imp": 0}, "Ghana": {"exp": 1069.0, "imp": 0}, "Singapur": {"exp": 5.0, "imp": 0}, "Egipto": {"exp": 362643.0, "imp": 0}, "Colombia": {"exp": 5.0, "imp": 0}, "Venezuela": {"exp": 5.0, "imp": 0}, "Rusia": {"exp": 888507.0, "imp": 0}, "Estados Unidos": {"exp": 6.0, "imp": 0}}, "040390": {"Filipinas": {"exp": 7426737.0, "imp": 0}, "Malasia": {"exp": 369140.0, "imp": 0}, "Paraguay": {"exp": 196310.0, "imp": 0}, "México": {"exp": 495749.0, "imp": 0}, "Tailandia": {"exp": 2951959.0, "imp": 0}, "Brasil": {"exp": 42586240.0, "imp": 680675.0}, "Singapur": {"exp": 1999416.0, "imp": 0}, "China": {"exp": 2382.0, "imp": 0}, "Myanmar": {"exp": 564980.0, "imp": 0}, "Arabia Saudita": {"exp": 296404.0, "imp": 0}, "Rusia": {"exp": 3.0, "imp": 0}, "Emiratos Árabes": {"exp": 220324.0, "imp": 0}, "Vietnam": {"exp": 1.0, "imp": 0}, "Baréin": {"exp": 9.0, "imp": 0}, "Egipto": {"exp": 310874.0, "imp": 0}, "Bangladesh": {"exp": 113300.0, "imp": 0}, "Japón": {"exp": 4.0, "imp": 0}, "Estados Unidos": {"exp": 0, "imp": 35006.0}, "Argentina": {"exp": 0, "imp": 685685.0}}, "040630": {"Chequia": {"exp": 1128.0, "imp": 0}, "Baréin": {"exp": 1589020.0, "imp": 0}, "Estados Unidos": {"exp": 264.0, "imp": 0}, "Filipinas": {"exp": 1313818.0, "imp": 0}, "Corea del Sur": {"exp": 44.0, "imp": 0}, "Arabia Saudita": {"exp": 880744.0, "imp": 0}, "Chile": {"exp": 39966288.0, "imp": 0}, "Rusia": {"exp": 46877829.0, "imp": 0}, "Jordania": {"exp": 76807.0, "imp": 0}, "Malasia": {"exp": 184.0, "imp": 0}, "Brasil": {"exp": 43018544.0, "imp": 410641.0}, "Bolivia": {"exp": 1768177.0, "imp": 0}, "Kuwait": {"exp": 551373.0, "imp": 0}, "Perú": {"exp": 5236347.0, "imp": 0}, "Mauricio": {"exp": 26435.0, "imp": 0}, "Qatar": {"exp": 93.0, "imp": 0}, "Paraguay": {"exp": 15648236.0, "imp": 0}, "Argentina": {"exp": 54683879.0, "imp": 2578.0}, "Japón": {"exp": 29.0, "imp": 0}, "Singapur": {"exp": 199.0, "imp": 0}, "Vietnam": {"exp": 72.0, "imp": 0}, "Tailandia": {"exp": 28.0, "imp": 0}, "Hong Kong": {"exp": 114.0, "imp": 0}, "Emiratos Árabes": {"exp": 55.0, "imp": 0}, "España": {"exp": 123.0, "imp": 81482.0}, "Bangladesh": {"exp": 55507.0, "imp": 0}, "México": {"exp": 2072.0, "imp": 0}, "Sri Lanka": {"exp": 19.0, "imp": 0}, "Suiza": {"exp": 0, "imp": 19896.0}, "Italia": {"exp": 0, "imp": 17738.0}, "Francia": {"exp": 0, "imp": 200716.0}, "Dinamarca": {"exp": 0, "imp": 22782.0}}, "040721": {"Reino Unido": {"exp": 32940.0, "imp": 0}, "Guinea Ecuatorial": {"exp": 205920.0, "imp": 0}, "Sierra Leona": {"exp": 285770.0, "imp": 0}, "Gambia": {"exp": 53760.0, "imp": 0}}, "040610": {"Argentina": {"exp": 5644012.0, "imp": 2959683.0}, "Japón": {"exp": 360.0, "imp": 0}, "Bolivia": {"exp": 354245.0, "imp": 0}, "Chile": {"exp": 7160525.0, "imp": 0}, "Jordania": {"exp": 7.0, "imp": 0}, "Paraguay": {"exp": 5132793.0, "imp": 0}, "Brasil": {"exp": 64399943.0, "imp": 636058.0}, "Perú": {"exp": 1008841.0, "imp": 0}, "Hong Kong": {"exp": 30.0, "imp": 0}, "Chequia": {"exp": 79.0, "imp": 0}, "Colombia": {"exp": 90.0, "imp": 0}, "Venezuela": {"exp": 3390.0, "imp": 0}, "Cuba": {"exp": 20.0, "imp": 0}, "Corea del Sur": {"exp": 35.0, "imp": 0}, "Rusia": {"exp": 20145.0, "imp": 0}, "Vietnam": {"exp": 1674451.0, "imp": 0}, "Panamá": {"exp": 96250.0, "imp": 0}, "Emiratos Árabes": {"exp": 15.0, "imp": 0}, "China": {"exp": 52538.0, "imp": 0}, "México": {"exp": 335558.0, "imp": 0}, "Estados Unidos": {"exp": 299.0, "imp": 0}, "Filipinas": {"exp": 32083.0, "imp": 0}, "Líbano": {"exp": 50500.0, "imp": 0}, "El Salvador": {"exp": 74.0, "imp": 0}, "Países Bajos": {"exp": 0, "imp": 158.0}, "Dinamarca": {"exp": 0, "imp": 68354.0}, "Francia": {"exp": 0, "imp": 26817.0}, "Italia": {"exp": 0, "imp": 14152.0}}, "040120": {"Brunei Darussalam": {"exp": 304646.0, "imp": 0}, "Angola": {"exp": 147675.0, "imp": 0}, "Filipinas": {"exp": 14068501.0, "imp": 0}, "Singapur": {"exp": 1269178.0, "imp": 0}, "Brasil": {"exp": 227706.0, "imp": 1095970.0}, "Venezuela": {"exp": 100.0, "imp": 0}, "Chile": {"exp": 24732.0, "imp": 0}, "China": {"exp": 4622572.0, "imp": 0}, "Vietnam": {"exp": 2740141.0, "imp": 0}, "Camboya": {"exp": 88448.0, "imp": 0}, "Argentina": {"exp": 2182699.0, "imp": 118496.0}, "Trinidad y Tobago": {"exp": 1411790.0, "imp": 0}, "Estados Unidos": {"exp": 3.0, "imp": 0}, "Francia": {"exp": 3.0, "imp": 203.0}, "Malasia": {"exp": 6.0, "imp": 0}, "Reino Unido": {"exp": 316.0, "imp": 0}, "Alemania": {"exp": 0, "imp": 714.0}}, "040690": {"Filipinas": {"exp": 20167818.0, "imp": 0}, "Sudáfrica": {"exp": 570.0, "imp": 0}, "Argentina": {"exp": 1012350.0, "imp": 8209511.0}, "Panamá": {"exp": 334.0, "imp": 0}, "Bolivia": {"exp": 2510768.0, "imp": 0}, "Japón": {"exp": 600.0, "imp": 0}, "Venezuela": {"exp": 2607742.0, "imp": 0}, "Angola": {"exp": 1444367.0, "imp": 0}, "Estados Unidos": {"exp": 26994479.0, "imp": 163808.0}, "Costa Rica": {"exp": 509.0, "imp": 0}, "Paraguay": {"exp": 9024294.0, "imp": 0}, "Cuba": {"exp": 10387395.0, "imp": 0}, "Colombia": {"exp": 603.0, "imp": 0}, "Vietnam": {"exp": 11592845.0, "imp": 0}, "Chile": {"exp": 5480230.0, "imp": 0}, "Senegal": {"exp": 4378.0, "imp": 0}, "Perú": {"exp": 27688422.0, "imp": 0}, "Brasil": {"exp": 88423740.0, "imp": 45101.0}, "México": {"exp": 154678282.0, "imp": 0}, "Mongolia": {"exp": 1063758.0, "imp": 0}, "China": {"exp": 17418685.0, "imp": 0}, "Malasia": {"exp": 199.0, "imp": 0}, "Rusia": {"exp": 63525758.0, "imp": 0}, "Arabia Saudita": {"exp": 163.0, "imp": 0}, "Suriname": {"exp": 36.0, "imp": 0}, "Emiratos Árabes": {"exp": 163.0, "imp": 0}, "Reino Unido": {"exp": 86.0, "imp": 7957.0}, "Líbano": {"exp": 76715.0, "imp": 0}, "Irak": {"exp": 152371.0, "imp": 0}, "Benin": {"exp": 38585.0, "imp": 0}, "Nigeria": {"exp": 21.0, "imp": 0}, "El Salvador": {"exp": 237.0, "imp": 0}, "Singapur": {"exp": 30.0, "imp": 0}, "Brunei Darussalam": {"exp": 954.0, "imp": 0}, "España": {"exp": 0, "imp": 79129.0}, "Dinamarca": {"exp": 0, "imp": 296317.0}, "Chipre": {"exp": 0, "imp": 6719.0}, "Suiza": {"exp": 0, "imp": 2469.0}, "Nueva Zelanda": {"exp": 0, "imp": 341746.0}, "Países Bajos": {"exp": 0, "imp": 407657.0}, "Grecia": {"exp": 0, "imp": 56584.0}, "Alemania": {"exp": 0, "imp": 41180.0}, "Francia": {"exp": 0, "imp": 364220.0}, "Italia": {"exp": 0, "imp": 160958.0}}, "040620": {"México": {"exp": 1101392.0, "imp": 0}, "Paraguay": {"exp": 146140.0, "imp": 0}, "Argentina": {"exp": 7445165.0, "imp": 56831.0}, "Chile": {"exp": 5889538.0, "imp": 0}, "Rusia": {"exp": 2480937.0, "imp": 0}, "Perú": {"exp": 75322.0, "imp": 0}, "Colombia": {"exp": 485985.0, "imp": 0}, "Brasil": {"exp": 5512011.0, "imp": 45970.0}, "Dinamarca": {"exp": 482688.0, "imp": 0}, "Singapur": {"exp": 5277.0, "imp": 0}, "Costa Rica": {"exp": 2785.0, "imp": 0}, "Estados Unidos": {"exp": 0, "imp": 36698.0}, "Italia": {"exp": 0, "imp": 2139.0}}, "040210": {"Irak": {"exp": 110000.0, "imp": 0}, "Malasia": {"exp": 2315529.0, "imp": 0}, "Pakistán": {"exp": 773326.0, "imp": 0}, "China": {"exp": 11861667.0, "imp": 0}, "Singapur": {"exp": 3235742.0, "imp": 0}, "Chile": {"exp": 3360158.0, "imp": 0}, "Brasil": {"exp": 204586097.0, "imp": 0}, "Colombia": {"exp": 1751948.0, "imp": 0}, "Myanmar": {"exp": 2281500.0, "imp": 0}, "Rusia": {"exp": 12361708.0, "imp": 0}, "Bolivia": {"exp": 17841249.0, "imp": 0}, "Bangladesh": {"exp": 756877.0, "imp": 0}, "Filipinas": {"exp": 2262328.0, "imp": 0}, "Paraguay": {"exp": 1319503.0, "imp": 0}, "México": {"exp": 6536178.0, "imp": 0}, "Argelia": {"exp": 91006840.0, "imp": 0}, "Brunei Darussalam": {"exp": 62085.0, "imp": 0}, "Argentina": {"exp": 98.0, "imp": 1147501.0}, "Vietnam": {"exp": 13210.0, "imp": 0}, "Afganistán": {"exp": 184844.0, "imp": 0}, "Egipto": {"exp": 433082.0, "imp": 0}, "Venezuela": {"exp": 2432052.0, "imp": 0}, "Francia": {"exp": 5.0, "imp": 80208.0}, "Tailandia": {"exp": 117612.0, "imp": 0}, "Baréin": {"exp": 1070942.0, "imp": 0}, "Mongolia": {"exp": 12.0, "imp": 0}, "Omán": {"exp": 825356.0, "imp": 0}, "Perú": {"exp": 1202.0, "imp": 0}, "Arabia Saudita": {"exp": 2970177.0, "imp": 0}, "Jordania": {"exp": 5.0, "imp": 0}, "Sudáfrica": {"exp": 1167776.0, "imp": 0}, "Panamá": {"exp": 135300.0, "imp": 0}, "India": {"exp": 28.0, "imp": 0}, "Emiratos Árabes": {"exp": 398413.0, "imp": 0}, "Mauricio": {"exp": 199631.0, "imp": 0}, "Trinidad y Tobago": {"exp": 2.0, "imp": 0}, "Cuba": {"exp": 4875141.0, "imp": 0}, "Qatar": {"exp": 95259.0, "imp": 0}, "Costa de Marfil": {"exp": 45776.0, "imp": 0}, "Georgia": {"exp": 851495.0, "imp": 0}, "Suriname": {"exp": 20903.0, "imp": 0}, "Níger": {"exp": 359356.0, "imp": 0}, "Nigeria": {"exp": 3410641.0, "imp": 0}, "El Salvador": {"exp": 371.0, "imp": 0}, "Estados Unidos": {"exp": 3.0, "imp": 545290.0}, "Japón": {"exp": 12.0, "imp": 0}, "Líbano": {"exp": 162002.0, "imp": 0}, "Polonia": {"exp": 0, "imp": 144250.0}}, "040410": {"Argelia": {"exp": 1036192.0, "imp": 0}, "Arabia Saudita": {"exp": 1050752.0, "imp": 0}, "Filipinas": {"exp": 29421041.0, "imp": 0}, "Paraguay": {"exp": 2674385.0, "imp": 0}, "Rusia": {"exp": 5786881.0, "imp": 0}, "Vietnam": {"exp": 6261222.0, "imp": 0}, "Costa Rica": {"exp": 1703962.0, "imp": 0}, "Egipto": {"exp": 137846.0, "imp": 0}, "Colombia": {"exp": 3833735.0, "imp": 0}, "Singapur": {"exp": 2799677.0, "imp": 0}, "Japón": {"exp": 68212.0, "imp": 0}, "Brasil": {"exp": 11911525.0, "imp": 0}, "Tailandia": {"exp": 2805054.0, "imp": 0}, "Pakistán": {"exp": 818181.0, "imp": 0}, "Malasia": {"exp": 1058085.0, "imp": 0}, "Siria": {"exp": 166480.0, "imp": 0}, "China": {"exp": 20878147.0, "imp": 0}, "Emiratos Árabes": {"exp": 2163172.0, "imp": 0}, "Bolivia": {"exp": 2531920.0, "imp": 0}, "Venezuela": {"exp": 2254478.0, "imp": 0}, "Myanmar": {"exp": 173511.0, "imp": 0}, "Chile": {"exp": 55418.0, "imp": 0}, "Estados Unidos": {"exp": 207.0, "imp": 311507.0}, "Sudáfrica": {"exp": 963214.0, "imp": 0}, "India": {"exp": 278216.0, "imp": 0}, "Brunei Darussalam": {"exp": 22.0, "imp": 0}, "Costa de Marfil": {"exp": 35000.0, "imp": 0}, "El Salvador": {"exp": 1575.0, "imp": 0}, "Países Bajos": {"exp": 0, "imp": 48450.0}, "Dinamarca": {"exp": 0, "imp": 318819.0}, "Canadá": {"exp": 0, "imp": 26479.0}, "Argentina": {"exp": 0, "imp": 844920.0}}, "041000": {"China": {"exp": 501012.0, "imp": 0}}, "040310": {"Argentina": {"exp": 1501014.0, "imp": 0}}, "040811": {"España": {"exp": 9058.0, "imp": 0}, "Brasil": {"exp": 0, "imp": 188137.0}, "Argentina": {"exp": 0, "imp": 65788.0}}, "040891": {"España": {"exp": 25802.0, "imp": 0}, "Brasil": {"exp": 0, "imp": 1270515.0}, "Argentina": {"exp": 0, "imp": 279996.0}}, "040490": {"Brasil": {"exp": 31738.0, "imp": 0}, "Sudáfrica": {"exp": 2.0, "imp": 0}, "México": {"exp": 1288.0, "imp": 0}, "España": {"exp": 0, "imp": 29856.0}, "Estados Unidos": {"exp": 0, "imp": 120403.0}, "Canadá": {"exp": 0, "imp": 31083.0}, "Argentina": {"exp": 0, "imp": 2153566.0}}, "040299": {"Reino Unido": {"exp": 408.0, "imp": 0}, "Emiratos Árabes": {"exp": 923520.0, "imp": 0}, "Brasil": {"exp": 0, "imp": 287784.0}}, "041090": {"Estados Unidos": {"exp": 1578.0, "imp": 0}, "Alemania": {"exp": 121028.0, "imp": 0}, "Croacia": {"exp": 23333.0, "imp": 0}, "China": {"exp": 0, "imp": 137400.0}}, "040320": {"Brasil": {"exp": 0, "imp": 341090.0}, "Alemania": {"exp": 0, "imp": 114.0}, "Argentina": {"exp": 0, "imp": 596050.0}}, "040819": {"Brasil": {"exp": 0, "imp": 1.0}}, "040711": {"Brasil": {"exp": 0, "imp": 165220.0}, "Argentina": {"exp": 0, "imp": 111937.0}}, "040899": {"Brasil": {"exp": 0, "imp": 1472723.0}}, "040640": {"Dinamarca": {"exp": 0, "imp": 432556.0}, "Francia": {"exp": 0, "imp": 39188.0}, "España": {"exp": 0, "imp": 471.0}, "Argentina": {"exp": 0, "imp": 784255.0}, "Italia": {"exp": 0, "imp": 18159.0}}, "040140": {"Argentina": {"exp": 0, "imp": 694973.0}}}