{"630720": {"España": {"exp": 2628.0, "imp": 19084.0}, "Panamá": {"exp": 94.0, "imp": 0}, "Guyana": {"exp": 47.0, "imp": 0}, "Alemania": {"exp": 40.0, "imp": 803.0}, "Paraguay": {"exp": 709.0, "imp": 0}, "Italia": {"exp": 56.0, "imp": 1323.0}, "Estados Unidos": {"exp": 125.0, "imp": 25897.0}, "Brasil": {"exp": 217.0, "imp": 22553.0}, "Reino Unido": {"exp": 4510.0, "imp": 43.0}, "China": {"exp": 0, "imp": 170421.0}, "Chequia": {"exp": 0, "imp": 52.0}, "Francia": {"exp": 0, "imp": 1575.0}, "Dinamarca": {"exp": 0, "imp": 12170.0}, "Grecia": {"exp": 0, "imp": 2933.0}, "Hungría": {"exp": 0, "imp": 1103.0}, "Lituania": {"exp": 0, "imp": 2915.0}, "Países Bajos": {"exp": 0, "imp": 680.0}, "Noruega": {"exp": 0, "imp": 1.0}, "Argentina": {"exp": 0, "imp": 2207.0}, "Australia": {"exp": 0, "imp": 2710.0}, "Bélgica": {"exp": 0, "imp": 2028.0}, "Hong Kong": {"exp": 0, "imp": 14656.0}, "Camboya": {"exp": 0, "imp": 2842.0}}, "630492": {"Argentina": {"exp": 287996.0, "imp": 46009.0}, "Turquía": {"exp": 1102.0, "imp": 1856.0}, "Marruecos": {"exp": 0, "imp": 139.0}, "China": {"exp": 0, "imp": 140025.0}, "Francia": {"exp": 0, "imp": 145.0}, "Nueva Zelanda": {"exp": 0, "imp": 86.0}, "España": {"exp": 0, "imp": 2345.0}, "Brasil": {"exp": 0, "imp": 47983.0}, "Dinamarca": {"exp": 0, "imp": 1610.0}, "Alemania": {"exp": 0, "imp": 29.0}, "Indonesia": {"exp": 0, "imp": 85.0}, "Lituania": {"exp": 0, "imp": 74.0}, "Paraguay": {"exp": 0, "imp": 1102.0}, "India": {"exp": 0, "imp": 234611.0}, "Estados Unidos": {"exp": 0, "imp": 17.0}, "Portugal": {"exp": 0, "imp": 2179.0}, "Austria": {"exp": 0, "imp": 163.0}, "Bangladesh": {"exp": 0, "imp": 16538.0}, "Italia": {"exp": 0, "imp": 287.0}}, "630419": {"Estados Unidos": {"exp": 30557.0, "imp": 3178.0}, "España": {"exp": 25.0, "imp": 842.0}, "Argentina": {"exp": 106719.0, "imp": 870.0}, "Italia": {"exp": 10.0, "imp": 0}, "Reino Unido": {"exp": 468.0, "imp": 0}, "Marruecos": {"exp": 0, "imp": 1312.0}, "China": {"exp": 0, "imp": 97557.0}, "Brasil": {"exp": 0, "imp": 88616.0}, "Pakistán": {"exp": 0, "imp": 5201.0}, "India": {"exp": 0, "imp": 57385.0}, "Turquía": {"exp": 0, "imp": 1915.0}, "Portugal": {"exp": 0, "imp": 38625.0}, "Australia": {"exp": 0, "imp": 81.0}, "Hong Kong": {"exp": 0, "imp": 807.0}}, "630532": {"Brasil": {"exp": 935130.0, "imp": 14602.0}, "Palau": {"exp": 19188.0, "imp": 0}, "Chile": {"exp": 18.0, "imp": 0}, "Japón": {"exp": 11.0, "imp": 0}, "Colombia": {"exp": 32767.0, "imp": 0}, "China": {"exp": 0, "imp": 67830.0}, "España": {"exp": 0, "imp": 532.0}, "Indonesia": {"exp": 0, "imp": 42536.0}, "México": {"exp": 0, "imp": 16956.0}, "Paraguay": {"exp": 0, "imp": 7497.0}, "India": {"exp": 0, "imp": 5096672.0}, "Turquía": {"exp": 0, "imp": 194122.0}, "Argentina": {"exp": 0, "imp": 49047.0}, "Italia": {"exp": 0, "imp": 428.0}}, "630222": {"Argentina": {"exp": 2740509.0, "imp": 291641.0}, "Brasil": {"exp": 59499.0, "imp": 129643.0}, "Chile": {"exp": 12028.0, "imp": 1224.0}, "Estados Unidos": {"exp": 0, "imp": 270.0}, "India": {"exp": 0, "imp": 227.0}, "Pakistán": {"exp": 0, "imp": 637958.0}, "Panamá": {"exp": 0, "imp": 2.0}, "China": {"exp": 0, "imp": 1399447.0}}, "630120": {"Alemania": {"exp": 1473.0, "imp": 0}, "Estados Unidos": {"exp": 360345.0, "imp": 1432.0}, "Reino Unido": {"exp": 62895.0, "imp": 0}, "Italia": {"exp": 85538.0, "imp": 0}, "Bélgica": {"exp": 3917.0, "imp": 0}, "Brasil": {"exp": 3623.0, "imp": 17121.0}, "España": {"exp": 10150.0, "imp": 0}, "Chile": {"exp": 86.0, "imp": 0}, "Canadá": {"exp": 1440.0, "imp": 0}, "Colombia": {"exp": 2.0, "imp": 0}, "Portugal": {"exp": 35.0, "imp": 0}, "China": {"exp": 0, "imp": 8629.0}, "Perú": {"exp": 0, "imp": 2319.0}, "Indonesia": {"exp": 0, "imp": 90.0}, "India": {"exp": 0, "imp": 3313.0}, "Argentina": {"exp": 0, "imp": 277.0}}, "630790": {"Chile": {"exp": 86920.0, "imp": 142509.0}, "Brasil": {"exp": 10492415.0, "imp": 736195.0}, "Panamá": {"exp": 51853.0, "imp": 703.0}, "Argentina": {"exp": 1383775.0, "imp": 652325.0}, "Paraguay": {"exp": 66692.0, "imp": 73000.0}, "Alemania": {"exp": 43896.0, "imp": 48980.0}, "España": {"exp": 919.0, "imp": 171032.0}, "Estados Unidos": {"exp": 886839.0, "imp": 502078.0}, "Rusia": {"exp": 100.0, "imp": 0}, "México": {"exp": 1916.0, "imp": 78236.0}, "Bolivia": {"exp": 238822.0, "imp": 0}, "Suiza": {"exp": 190.0, "imp": 704.0}, "Guyana": {"exp": 1.0, "imp": 0}, "Perú": {"exp": 15811.0, "imp": 5765.0}, "Corea del Sur": {"exp": 5070.0, "imp": 3593.0}, "Japón": {"exp": 2599.0, "imp": 1691.0}, "China": {"exp": 872695.0, "imp": 5160366.0}, "Hong Kong": {"exp": 143176.0, "imp": 97171.0}, "Reino Unido": {"exp": 23034.0, "imp": 9286.0}, "Bulgaria": {"exp": 70.0, "imp": 274.0}, "Colombia": {"exp": 104116.0, "imp": 222150.0}, "Ecuador": {"exp": 816.0, "imp": 1.0}, "Emiratos Árabes": {"exp": 225.0, "imp": 2217.0}, "Nicaragua": {"exp": 959.0, "imp": 0}, "Italia": {"exp": 1101.0, "imp": 29970.0}, "Guatemala": {"exp": 6011.0, "imp": 218.0}, "Austria": {"exp": 53.0, "imp": 5973.0}, "Egipto": {"exp": 222.0, "imp": 0}, "Venezuela": {"exp": 120.0, "imp": 134.0}, "Países Bajos": {"exp": 390.0, "imp": 6896.0}, "Finlandia": {"exp": 67.0, "imp": 2893.0}, "Singapur": {"exp": 74848.0, "imp": 3278.0}, "Marruecos": {"exp": 0, "imp": 685.0}, "Bosnia Herzegovina": {"exp": 0, "imp": 36.0}, "Chequia": {"exp": 0, "imp": 7318.0}, "Francia": {"exp": 0, "imp": 10848.0}, "Malasia": {"exp": 0, "imp": 229.0}, "Nueva Zelanda": {"exp": 0, "imp": 137.0}, "Filipinas": {"exp": 0, "imp": 3997.0}, "Túnez": {"exp": 0, "imp": 560.0}, "Dinamarca": {"exp": 0, "imp": 5735.0}, "Georgia": {"exp": 0, "imp": 190.0}, "Grecia": {"exp": 0, "imp": 36.0}, "Hungría": {"exp": 0, "imp": 10106.0}, "Indonesia": {"exp": 0, "imp": 7505.0}, "Luxemburgo": {"exp": 0, "imp": 10139.0}, "Madagascar": {"exp": 0, "imp": 235.0}, "Noruega": {"exp": 0, "imp": 1.0}, "Pakistán": {"exp": 0, "imp": 8024.0}, "Polonia": {"exp": 0, "imp": 2899.0}, "India": {"exp": 0, "imp": 70829.0}, "Vietnam": {"exp": 0, "imp": 20317.0}, "Suecia": {"exp": 0, "imp": 5230.0}, "Turquía": {"exp": 0, "imp": 22128.0}, "Ucrania": {"exp": 0, "imp": 7108.0}, "Estonia": {"exp": 0, "imp": 5091.0}, "Portugal": {"exp": 0, "imp": 2497.0}, "Rumania": {"exp": 0, "imp": 18398.0}, "Tailandia": {"exp": 0, "imp": 5426.0}, "Canadá": {"exp": 0, "imp": 17803.0}, "Eslovaquia": {"exp": 0, "imp": 391.0}, "Israel": {"exp": 0, "imp": 1596.0}, "Australia": {"exp": 0, "imp": 458.0}, "Bangladesh": {"exp": 0, "imp": 9218.0}, "Bélgica": {"exp": 0, "imp": 3115.0}, "Bielorrusia": {"exp": 0, "imp": 12.0}, "Camboya": {"exp": 0, "imp": 1022.0}, "Sri Lanka": {"exp": 0, "imp": 2298.0}}, "630231": {"Alemania": {"exp": 200.0, "imp": 0}, "Brasil": {"exp": 278062.0, "imp": 150470.0}, "Argentina": {"exp": 2098918.0, "imp": 162961.0}, "Reino Unido": {"exp": 138.0, "imp": 0}, "Estados Unidos": {"exp": 60.0, "imp": 12246.0}, "China": {"exp": 0, "imp": 429283.0}, "Francia": {"exp": 0, "imp": 50.0}, "España": {"exp": 0, "imp": 4182.0}, "Dinamarca": {"exp": 0, "imp": 544.0}, "Indonesia": {"exp": 0, "imp": 1198.0}, "Pakistán": {"exp": 0, "imp": 438460.0}, "Paraguay": {"exp": 0, "imp": 54725.0}, "India": {"exp": 0, "imp": 102162.0}, "Turquía": {"exp": 0, "imp": 1497.0}, "Egipto": {"exp": 0, "imp": 20404.0}, "Portugal": {"exp": 0, "imp": 56339.0}, "Siria": {"exp": 0, "imp": 96.0}, "Bangladesh": {"exp": 0, "imp": 10072.0}, "Hong Kong": {"exp": 0, "imp": 32878.0}}, "630240": {"Francia": {"exp": 15.0, "imp": 0}, "España": {"exp": 7.0, "imp": 0}, "Rusia": {"exp": 25.0, "imp": 0}, "Argentina": {"exp": 20.0, "imp": 6366.0}, "Reino Unido": {"exp": 84.0, "imp": 0}, "China": {"exp": 0, "imp": 5813.0}, "Indonesia": {"exp": 0, "imp": 41.0}, "India": {"exp": 0, "imp": 16122.0}, "Estados Unidos": {"exp": 0, "imp": 1031.0}}, "630493": {"Argentina": {"exp": 1376149.0, "imp": 18468.0}, "Marruecos": {"exp": 0, "imp": 84.0}, "China": {"exp": 0, "imp": 833594.0}, "Francia": {"exp": 0, "imp": 284.0}, "Perú": {"exp": 0, "imp": 446.0}, "España": {"exp": 0, "imp": 17411.0}, "Reino Unido": {"exp": 0, "imp": 71.0}, "Brasil": {"exp": 0, "imp": 16297.0}, "Alemania": {"exp": 0, "imp": 2851.0}, "India": {"exp": 0, "imp": 4995.0}, "Suecia": {"exp": 0, "imp": 5166.0}, "Turquía": {"exp": 0, "imp": 61958.0}, "Ucrania": {"exp": 0, "imp": 148.0}, "Estados Unidos": {"exp": 0, "imp": 810.0}, "Chile": {"exp": 0, "imp": 2915.0}, "Japón": {"exp": 0, "imp": 1392.0}, "Bangladesh": {"exp": 0, "imp": 68.0}, "Italia": {"exp": 0, "imp": 2949.0}, "Bélgica": {"exp": 0, "imp": 311.0}}, "630710": {"Rep. Dominicana": {"exp": 16052.0, "imp": 0}, "Ecuador": {"exp": 53170.0, "imp": 0}, "Argentina": {"exp": 28693.0, "imp": 99439.0}, "Paraguay": {"exp": 59261.0, "imp": 18795.0}, "Reino Unido": {"exp": 471.0, "imp": 3014.0}, "Chile": {"exp": 115818.0, "imp": 0}, "Brasil": {"exp": 56926.0, "imp": 31153.0}, "México": {"exp": 1102.0, "imp": 239.0}, "Perú": {"exp": 6428.0, "imp": 0}, "Italia": {"exp": 0, "imp": 12627.0}, "Austria": {"exp": 0, "imp": 123.0}, "Estados Unidos": {"exp": 0, "imp": 48134.0}, "Portugal": {"exp": 0, "imp": 1029.0}, "Israel": {"exp": 0, "imp": 5345.0}, "Tailandia": {"exp": 0, "imp": 165.0}, "Suecia": {"exp": 0, "imp": 11.0}, "Suiza": {"exp": 0, "imp": 240.0}, "Vietnam": {"exp": 0, "imp": 6531.0}, "España": {"exp": 0, "imp": 3416.0}, "Rumania": {"exp": 0, "imp": 16.0}, "India": {"exp": 0, "imp": 81408.0}, "Pakistán": {"exp": 0, "imp": 3566.0}, "Panamá": {"exp": 0, "imp": 967.0}, "Malasia": {"exp": 0, "imp": 88.0}, "Japón": {"exp": 0, "imp": 1273.0}, "Corea del Sur": {"exp": 0, "imp": 1175.0}, "Indonesia": {"exp": 0, "imp": 635.0}, "Grecia": {"exp": 0, "imp": 26.0}, "Hong Kong": {"exp": 0, "imp": 4695.0}, "Países Bajos": {"exp": 0, "imp": 12.0}, "Bangladesh": {"exp": 0, "imp": 40.0}, "Francia": {"exp": 0, "imp": 1079.0}, "Alemania": {"exp": 0, "imp": 31430.0}, "Estonia": {"exp": 0, "imp": 369.0}, "Colombia": {"exp": 0, "imp": 8240.0}, "China": {"exp": 0, "imp": 1024991.0}, "Canadá": {"exp": 0, "imp": 147.0}}, "630491": {"Argentina": {"exp": 12670.0, "imp": 3575.0}, "España": {"exp": 147.0, "imp": 492.0}, "Alemania": {"exp": 15.0, "imp": 0}, "Reino Unido": {"exp": 211.0, "imp": 0}, "Italia": {"exp": 0, "imp": 1777.0}, "Estados Unidos": {"exp": 0, "imp": 107.0}, "Portugal": {"exp": 0, "imp": 538.0}, "Vietnam": {"exp": 0, "imp": 261.0}, "India": {"exp": 0, "imp": 19332.0}, "Polonia": {"exp": 0, "imp": 75.0}, "Pakistán": {"exp": 0, "imp": 556.0}, "Marruecos": {"exp": 0, "imp": 285.0}, "Turquía": {"exp": 0, "imp": 846.0}, "Francia": {"exp": 0, "imp": 481.0}, "China": {"exp": 0, "imp": 437972.0}, "Chile": {"exp": 0, "imp": 249.0}, "Brasil": {"exp": 0, "imp": 518.0}}, "630253": {"Argentina": {"exp": 83400.0, "imp": 10011.0}, "Nueva Zelanda": {"exp": 329.0, "imp": 0}, "China": {"exp": 0, "imp": 500716.0}, "Filipinas": {"exp": 0, "imp": 1536.0}, "España": {"exp": 0, "imp": 31487.0}, "Reino Unido": {"exp": 0, "imp": 734.0}, "Brasil": {"exp": 0, "imp": 88209.0}, "Indonesia": {"exp": 0, "imp": 239.0}, "Pakistán": {"exp": 0, "imp": 5816.0}, "India": {"exp": 0, "imp": 47033.0}, "Vietnam": {"exp": 0, "imp": 194.0}, "Turquía": {"exp": 0, "imp": 3470.0}, "Estados Unidos": {"exp": 0, "imp": 2920.0}, "Portugal": {"exp": 0, "imp": 391.0}, "Bangladesh": {"exp": 0, "imp": 5649.0}, "Italia": {"exp": 0, "imp": 100.0}, "Hong Kong": {"exp": 0, "imp": 13641.0}}, "630232": {"Argentina": {"exp": 704181.0, "imp": 34048.0}, "Chile": {"exp": 2595.0, "imp": 3581.0}, "Brasil": {"exp": 1487.0, "imp": 161163.0}, "China": {"exp": 77258.0, "imp": 1427821.0}, "Estados Unidos": {"exp": 0, "imp": 6569.0}, "España": {"exp": 0, "imp": 3360.0}, "India": {"exp": 0, "imp": 18351.0}, "Pakistán": {"exp": 0, "imp": 472448.0}, "Bangladesh": {"exp": 0, "imp": 1025.0}, "Turquía": {"exp": 0, "imp": 2390.0}, "Egipto": {"exp": 0, "imp": 2286.0}, "Francia": {"exp": 0, "imp": 253.0}}, "631090": {"Estados Unidos": {"exp": 128.0, "imp": 103.0}, "Chile": {"exp": 168.0, "imp": 0}, "Paraguay": {"exp": 2036.0, "imp": 0}, "Austria": {"exp": 100.0, "imp": 0}, "Brasil": {"exp": 7400.0, "imp": 52372.0}, "Italia": {"exp": 3.0, "imp": 280.0}, "Alemania": {"exp": 0, "imp": 78.0}, "España": {"exp": 0, "imp": 9829.0}, "Panamá": {"exp": 0, "imp": 10.0}, "Japón": {"exp": 0, "imp": 50.0}, "Guatemala": {"exp": 0, "imp": 40278.0}, "Hong Kong": {"exp": 0, "imp": 25076.0}, "China": {"exp": 0, "imp": 581445.0}, "Polonia": {"exp": 0, "imp": 35.0}, "Bélgica": {"exp": 0, "imp": 12.0}, "Emiratos Árabes": {"exp": 0, "imp": 25104.0}, "Chequia": {"exp": 0, "imp": 8903.0}, "Dinamarca": {"exp": 0, "imp": 658.0}}, "631010": {"Estados Unidos": {"exp": 1380.0, "imp": 0}, "China": {"exp": 0, "imp": 291.0}, "Argentina": {"exp": 0, "imp": 2888.0}}, "630539": {"Alemania": {"exp": 5929.0, "imp": 63.0}, "Argentina": {"exp": 1300.0, "imp": 1851.0}, "Irak": {"exp": 216.0, "imp": 0}, "India": {"exp": 37.0, "imp": 601.0}, "Bolivia": {"exp": 316.0, "imp": 0}, "Israel": {"exp": 189.0, "imp": 0}, "Reino Unido": {"exp": 44.0, "imp": 0}, "China": {"exp": 70.0, "imp": 97175.0}, "España": {"exp": 0, "imp": 4530.0}, "Pakistán": {"exp": 0, "imp": 44377.0}, "Hong Kong": {"exp": 0, "imp": 28.0}, "Francia": {"exp": 0, "imp": 6039.0}, "Brasil": {"exp": 0, "imp": 517.0}, "Austria": {"exp": 0, "imp": 441.0}, "Estados Unidos": {"exp": 0, "imp": 7678.0}}, "630900": {"Francia": {"exp": 355.0, "imp": 0}, "Brasil": {"exp": 1354.0, "imp": 1312.0}, "Estados Unidos": {"exp": 1560.0, "imp": 53626.0}, "España": {"exp": 570.0, "imp": 921.0}, "Argentina": {"exp": 540.0, "imp": 0}, "Reino Unido": {"exp": 304.0, "imp": 0}, "Bélgica": {"exp": 60.0, "imp": 0}, "Italia": {"exp": 60.0, "imp": 235.0}, "China": {"exp": 0, "imp": 8555.0}, "India": {"exp": 0, "imp": 129.0}, "Emiratos Árabes": {"exp": 0, "imp": 18427.0}}, "630260": {"Paraguay": {"exp": 401.0, "imp": 44248.0}, "Alemania": {"exp": 150.0, "imp": 193.0}, "Estados Unidos": {"exp": 184.0, "imp": 14727.0}, "España": {"exp": 748.0, "imp": 13720.0}, "Chile": {"exp": 848.0, "imp": 0}, "Brasil": {"exp": 30.0, "imp": 5187372.0}, "Perú": {"exp": 94.0, "imp": 0}, "Argentina": {"exp": 149247.0, "imp": 20488.0}, "Nueva Zelanda": {"exp": 58.0, "imp": 0}, "Canadá": {"exp": 61.0, "imp": 0}, "Italia": {"exp": 0, "imp": 2147.0}, "Suiza": {"exp": 0, "imp": 280.0}, "Pakistán": {"exp": 0, "imp": 338704.0}, "Panamá": {"exp": 0, "imp": 1.0}, "Hong Kong": {"exp": 0, "imp": 17195.0}, "Francia": {"exp": 0, "imp": 5431.0}, "China": {"exp": 0, "imp": 1985597.0}, "Portugal": {"exp": 0, "imp": 154304.0}, "Vietnam": {"exp": 0, "imp": 199.0}, "India": {"exp": 0, "imp": 240243.0}, "Bangladesh": {"exp": 0, "imp": 15145.0}, "Bélgica": {"exp": 0, "imp": 5443.0}, "Reino Unido": {"exp": 0, "imp": 555.0}, "Turquía": {"exp": 0, "imp": 28231.0}, "Egipto": {"exp": 0, "imp": 1667.0}, "Tailandia": {"exp": 0, "imp": 1537.0}, "Emiratos Árabes": {"exp": 0, "imp": 7.0}, "Dinamarca": {"exp": 0, "imp": 191.0}, "Australia": {"exp": 0, "imp": 1861.0}}, "630190": {"Brasil": {"exp": 722.0, "imp": 0}, "México": {"exp": 673.0, "imp": 0}, "Estados Unidos": {"exp": 1695.0, "imp": 6210.0}, "España": {"exp": 420.0, "imp": 123.0}, "Argentina": {"exp": 16.0, "imp": 0}, "China": {"exp": 0, "imp": 129872.0}, "Reino Unido": {"exp": 0, "imp": 10121.0}, "Dinamarca": {"exp": 0, "imp": 374.0}, "Lituania": {"exp": 0, "imp": 1968.0}, "Noruega": {"exp": 0, "imp": 1.0}, "India": {"exp": 0, "imp": 26850.0}, "Portugal": {"exp": 0, "imp": 1051.0}, "Italia": {"exp": 0, "imp": 1635.0}, "Bélgica": {"exp": 0, "imp": 316.0}, "Corea del Sur": {"exp": 0, "imp": 1590.0}, "Camboya": {"exp": 0, "imp": 1184.0}}, "630590": {"Estados Unidos": {"exp": 119.0, "imp": 843.0}, "Brasil": {"exp": 2.0, "imp": 1776.0}, "España": {"exp": 306.0, "imp": 192.0}, "Perú": {"exp": 4462.0, "imp": 0}, "Chile": {"exp": 87.0, "imp": 0}, "Alemania": {"exp": 77.0, "imp": 54.0}, "China": {"exp": 0, "imp": 75264.0}, "Reino Unido": {"exp": 0, "imp": 580.0}, "Bulgaria": {"exp": 0, "imp": 33.0}, "Hungría": {"exp": 0, "imp": 2657.0}, "India": {"exp": 0, "imp": 681.0}, "Argentina": {"exp": 0, "imp": 31.0}, "Italia": {"exp": 0, "imp": 106.0}, "Bélgica": {"exp": 0, "imp": 20.0}, "Corea del Sur": {"exp": 0, "imp": 159.0}}, "630533": {"Sudáfrica": {"exp": 20.0, "imp": 0}, "Irak": {"exp": 243282.0, "imp": 0}, "Senegal": {"exp": 618575.0, "imp": 0}, "Brasil": {"exp": 345481.0, "imp": 2545832.0}, "Israel": {"exp": 1636.0, "imp": 0}, "España": {"exp": 410117.0, "imp": 6080.0}, "Cuba": {"exp": 3180180.0, "imp": 0}, "Sierra Leona": {"exp": 1841538.0, "imp": 0}, "Turquía": {"exp": 66343.0, "imp": 0}, "Perú": {"exp": 158818.0, "imp": 242.0}, "Paraguay": {"exp": 528133.0, "imp": 0}, "Nueva Zelanda": {"exp": 27493.0, "imp": 0}, "México": {"exp": 88.0, "imp": 0}, "Reino Unido": {"exp": 16815.0, "imp": 0}, "Angola": {"exp": 5920.0, "imp": 0}, "Argelia": {"exp": 340.0, "imp": 0}, "Venezuela": {"exp": 272.0, "imp": 0}, "Mali": {"exp": 80300.0, "imp": 0}, "Rep. Dominicana": {"exp": 165.0, "imp": 0}, "Cabo Verde": {"exp": 2650.0, "imp": 0}, "Chile": {"exp": 1978.0, "imp": 2754.0}, "Rusia": {"exp": 2450.0, "imp": 0}, "China": {"exp": 0, "imp": 357710.0}, "India": {"exp": 0, "imp": 250106.0}, "Argentina": {"exp": 0, "imp": 23184.0}, "Indonesia": {"exp": 0, "imp": 493051.0}, "Bolivia": {"exp": 0, "imp": 156090.0}}, "630140": {"Argentina": {"exp": 3276573.0, "imp": 5775.0}, "Estados Unidos": {"exp": 3595.0, "imp": 6066.0}, "Paraguay": {"exp": 4469.0, "imp": 0}, "Italia": {"exp": 575.0, "imp": 4750.0}, "Reino Unido": {"exp": 610.0, "imp": 0}, "Bélgica": {"exp": 160.0, "imp": 0}, "India": {"exp": 0, "imp": 25480.0}, "Turquía": {"exp": 0, "imp": 78.0}, "España": {"exp": 0, "imp": 264.0}, "Indonesia": {"exp": 0, "imp": 85.0}, "Hong Kong": {"exp": 0, "imp": 460.0}, "China": {"exp": 0, "imp": 1871328.0}, "Brasil": {"exp": 0, "imp": 55818.0}, "Bangladesh": {"exp": 0, "imp": 125.0}}, "630520": {"Paraguay": {"exp": 503.0, "imp": 0}, "Alemania": {"exp": 94.0, "imp": 0}, "Irak": {"exp": 705.0, "imp": 0}, "Italia": {"exp": 0, "imp": 14.0}, "España": {"exp": 0, "imp": 601.0}, "Lituania": {"exp": 0, "imp": 1.0}, "Indonesia": {"exp": 0, "imp": 546.0}, "China": {"exp": 0, "imp": 10585.0}, "Argentina": {"exp": 0, "imp": 686.0}, "India": {"exp": 0, "imp": 116.0}, "Brasil": {"exp": 0, "imp": 3215.0}, "Bosnia Herzegovina": {"exp": 0, "imp": 54.0}, "Reino Unido": {"exp": 0, "imp": 9.0}, "Tailandia": {"exp": 0, "imp": 10.0}}, "630612": {"Alemania": {"exp": 1493.0, "imp": 2451.0}, "Paraguay": {"exp": 184.0, "imp": 0}, "Letonia": {"exp": 50.0, "imp": 0}, "China": {"exp": 250.0, "imp": 942379.0}, "Perú": {"exp": 557.0, "imp": 0}, "Brasil": {"exp": 379.0, "imp": 98943.0}, "Argentina": {"exp": 223.0, "imp": 58840.0}, "Polonia": {"exp": 0, "imp": 29.0}, "Reino Unido": {"exp": 0, "imp": 1.0}, "Turquía": {"exp": 0, "imp": 129.0}, "España": {"exp": 0, "imp": 30626.0}, "Eslovenia": {"exp": 0, "imp": 120.0}, "Colombia": {"exp": 0, "imp": 1118.0}, "Hong Kong": {"exp": 0, "imp": 40822.0}, "Estados Unidos": {"exp": 0, "imp": 3006.0}, "Australia": {"exp": 0, "imp": 1422.0}, "Corea del Sur": {"exp": 0, "imp": 20953.0}}, "630110": {"Estados Unidos": {"exp": 8216.0, "imp": 23594.0}, "México": {"exp": 235.0, "imp": 11346.0}, "Alemania": {"exp": 476.0, "imp": 0}, "España": {"exp": 0, "imp": 5456.0}, "Hong Kong": {"exp": 0, "imp": 252.0}, "Hungría": {"exp": 0, "imp": 593.0}, "China": {"exp": 0, "imp": 788577.0}, "Argentina": {"exp": 0, "imp": 307.0}}, "630210": {"Estados Unidos": {"exp": 84319.0, "imp": 12536.0}, "España": {"exp": 120.0, "imp": 62.0}, "Canadá": {"exp": 122.0, "imp": 256.0}, "Reino Unido": {"exp": 40.0, "imp": 2531.0}, "Argentina": {"exp": 798.0, "imp": 174.0}, "Polonia": {"exp": 0, "imp": 3503.0}, "India": {"exp": 0, "imp": 13224.0}, "Noruega": {"exp": 0, "imp": 1.0}, "China": {"exp": 0, "imp": 220256.0}, "Brasil": {"exp": 0, "imp": 27035.0}, "Bélgica": {"exp": 0, "imp": 813.0}}, "630312": {"Alemania": {"exp": 67.0, "imp": 0}, "Argentina": {"exp": 380.0, "imp": 77699.0}, "Canadá": {"exp": 20.0, "imp": 0}, "China": {"exp": 0, "imp": 255465.0}, "Brasil": {"exp": 0, "imp": 4636.0}, "Estados Unidos": {"exp": 0, "imp": 4831.0}}, "630392": {"Bolivia": {"exp": 18767.0, "imp": 0}, "Argentina": {"exp": 736557.0, "imp": 122159.0}, "Estados Unidos": {"exp": 670.0, "imp": 950.0}, "Chile": {"exp": 533.0, "imp": 0}, "Italia": {"exp": 0, "imp": 1505.0}, "Hungría": {"exp": 0, "imp": 7822.0}, "Portugal": {"exp": 0, "imp": 327.0}, "Rumania": {"exp": 0, "imp": 827.0}, "India": {"exp": 0, "imp": 22246.0}, "Pakistán": {"exp": 0, "imp": 142.0}, "Indonesia": {"exp": 0, "imp": 572.0}, "Hong Kong": {"exp": 0, "imp": 7572.0}, "Países Bajos": {"exp": 0, "imp": 181.0}, "Bangladesh": {"exp": 0, "imp": 594.0}, "Alemania": {"exp": 0, "imp": 140.0}, "China": {"exp": 0, "imp": 3375624.0}, "Brasil": {"exp": 0, "imp": 4451.0}}, "630221": {"Argentina": {"exp": 1393005.0, "imp": 41578.0}, "Brasil": {"exp": 2416599.0, "imp": 282892.0}, "Reino Unido": {"exp": 568.0, "imp": 0}, "Paraguay": {"exp": 196.0, "imp": 0}, "China": {"exp": 0, "imp": 142373.0}, "Francia": {"exp": 0, "imp": 724.0}, "España": {"exp": 0, "imp": 25918.0}, "Bulgaria": {"exp": 0, "imp": 2024.0}, "Indonesia": {"exp": 0, "imp": 3202.0}, "Pakistán": {"exp": 0, "imp": 232383.0}, "India": {"exp": 0, "imp": 169595.0}, "Turquía": {"exp": 0, "imp": 24577.0}, "Estados Unidos": {"exp": 0, "imp": 6.0}, "Portugal": {"exp": 0, "imp": 918.0}, "Bangladesh": {"exp": 0, "imp": 19199.0}, "Italia": {"exp": 0, "imp": 583.0}, "Camboya": {"exp": 0, "imp": 559.0}}, "630293": {"Argentina": {"exp": 293902.0, "imp": 2979.0}, "Rep. Dominicana": {"exp": 2.0, "imp": 0}, "Chile": {"exp": 20204.0, "imp": 3774.0}, "Brasil": {"exp": 11.0, "imp": 42203.0}, "España": {"exp": 0, "imp": 130.0}, "Eslovenia": {"exp": 0, "imp": 372.0}, "China": {"exp": 0, "imp": 1102353.0}, "India": {"exp": 0, "imp": 2899.0}, "Portugal": {"exp": 0, "imp": 332.0}, "Canadá": {"exp": 0, "imp": 36.0}, "Colombia": {"exp": 0, "imp": 46.0}, "Túnez": {"exp": 0, "imp": 1344.0}, "Turquía": {"exp": 0, "imp": 238.0}, "Suiza": {"exp": 0, "imp": 773.0}, "Noruega": {"exp": 0, "imp": 1.0}, "Panamá": {"exp": 0, "imp": 314.0}, "Italia": {"exp": 0, "imp": 14.0}, "Hong Kong": {"exp": 0, "imp": 1147.0}, "Estados Unidos": {"exp": 0, "imp": 3781.0}, "Indonesia": {"exp": 0, "imp": 2995.0}, "Israel": {"exp": 0, "imp": 295.0}, "Vietnam": {"exp": 0, "imp": 280.0}}, "630629": {"Brasil": {"exp": 604.0, "imp": 0}, "Alemania": {"exp": 30.0, "imp": 0}, "Argentina": {"exp": 50.0, "imp": 0}, "España": {"exp": 5.0, "imp": 1079.0}, "Francia": {"exp": 0, "imp": 4684.0}, "Italia": {"exp": 0, "imp": 2526.0}, "Chequia": {"exp": 0, "imp": 370.0}, "Estados Unidos": {"exp": 0, "imp": 6633.0}, "China": {"exp": 0, "imp": 476097.0}, "Bangladesh": {"exp": 0, "imp": 2413.0}, "Australia": {"exp": 0, "imp": 175.0}}, "630619": {"Paraguay": {"exp": 767.0, "imp": 0}, "Argentina": {"exp": 52509.0, "imp": 1769.0}, "China": {"exp": 0, "imp": 160114.0}, "España": {"exp": 0, "imp": 1733.0}, "Reino Unido": {"exp": 0, "imp": 387.0}, "Brasil": {"exp": 0, "imp": 5038.0}, "Vietnam": {"exp": 0, "imp": 4696.0}, "Estados Unidos": {"exp": 0, "imp": 254.0}, "Chile": {"exp": 0, "imp": 1995.0}, "Italia": {"exp": 0, "imp": 133.0}}, "630690": {"Argentina": {"exp": 12034.0, "imp": 1954.0}, "China": {"exp": 0, "imp": 313350.0}, "Francia": {"exp": 0, "imp": 107.0}, "España": {"exp": 0, "imp": 6272.0}, "Reino Unido": {"exp": 0, "imp": 275.0}, "Brasil": {"exp": 0, "imp": 13199.0}, "Alemania": {"exp": 0, "imp": 1149.0}, "Indonesia": {"exp": 0, "imp": 221.0}, "Países Bajos": {"exp": 0, "imp": 1224.0}, "Pakistán": {"exp": 0, "imp": 231.0}, "India": {"exp": 0, "imp": 2184.0}, "Estados Unidos": {"exp": 0, "imp": 86502.0}, "Australia": {"exp": 0, "imp": 24.0}, "Austria": {"exp": 0, "imp": 57.0}, "Bangladesh": {"exp": 0, "imp": 10476.0}, "Italia": {"exp": 0, "imp": 6.0}, "Hong Kong": {"exp": 0, "imp": 10185.0}}, "630130": {"Paraguay": {"exp": 32.0, "imp": 969.0}, "Argentina": {"exp": 27044.0, "imp": 41242.0}, "España": {"exp": 0, "imp": 15144.0}, "China": {"exp": 0, "imp": 146354.0}, "Brasil": {"exp": 0, "imp": 26517.0}, "India": {"exp": 0, "imp": 110756.0}, "Portugal": {"exp": 0, "imp": 6305.0}, "Dinamarca": {"exp": 0, "imp": 2300.0}, "Austria": {"exp": 0, "imp": 9151.0}, "Bangladesh": {"exp": 0, "imp": 13.0}, "Turquía": {"exp": 0, "imp": 5050.0}, "Perú": {"exp": 0, "imp": 2370.0}, "Pakistán": {"exp": 0, "imp": 5144.0}, "Marruecos": {"exp": 0, "imp": 402.0}, "Países Bajos": {"exp": 0, "imp": 1906.0}, "Estados Unidos": {"exp": 0, "imp": 1938.0}, "Alemania": {"exp": 0, "imp": 293.0}, "Francia": {"exp": 0, "imp": 108.0}, "Indonesia": {"exp": 0, "imp": 38.0}}, "630239": {"Estados Unidos": {"exp": 88.0, "imp": 409.0}, "Brasil": {"exp": 27268.0, "imp": 39163.0}, "España": {"exp": 1076.0, "imp": 12755.0}, "China": {"exp": 0, "imp": 73163.0}, "Francia": {"exp": 0, "imp": 1176.0}, "Filipinas": {"exp": 0, "imp": 195.0}, "Turquía": {"exp": 0, "imp": 1006.0}, "Portugal": {"exp": 0, "imp": 11914.0}, "Argentina": {"exp": 0, "imp": 14707.0}, "Bangladesh": {"exp": 0, "imp": 6740.0}, "Italia": {"exp": 0, "imp": 1276.0}, "Camboya": {"exp": 0, "imp": 139020.0}}, "630399": {"Chile": {"exp": 22134.0, "imp": 0}, "Reino Unido": {"exp": 244.0, "imp": 0}, "India": {"exp": 0, "imp": 1265.0}, "Portugal": {"exp": 0, "imp": 192.0}, "Francia": {"exp": 0, "imp": 184.0}, "Egipto": {"exp": 0, "imp": 8196.0}, "España": {"exp": 0, "imp": 2168.0}, "Lituania": {"exp": 0, "imp": 234.0}, "Japón": {"exp": 0, "imp": 108.0}, "Italia": {"exp": 0, "imp": 50.0}, "Indonesia": {"exp": 0, "imp": 740.0}, "Estados Unidos": {"exp": 0, "imp": 5406.0}, "China": {"exp": 0, "imp": 139965.0}, "Brasil": {"exp": 0, "imp": 1957.0}, "Austria": {"exp": 0, "imp": 223.0}, "Argentina": {"exp": 0, "imp": 419.0}}, "630640": {"Argentina": {"exp": 50.0, "imp": 0}, "Estados Unidos": {"exp": 0, "imp": 746.0}, "Irlanda": {"exp": 0, "imp": 327.0}, "Hong Kong": {"exp": 0, "imp": 27007.0}, "China": {"exp": 0, "imp": 484381.0}}, "630319": {"Argentina": {"exp": 20.0, "imp": 2917.0}, "España": {"exp": 200.0, "imp": 5718.0}, "India": {"exp": 0, "imp": 5381.0}, "Alemania": {"exp": 0, "imp": 21048.0}, "Italia": {"exp": 0, "imp": 13650.0}, "Estados Unidos": {"exp": 0, "imp": 7612.0}, "China": {"exp": 0, "imp": 29427.0}, "Brasil": {"exp": 0, "imp": 6392.0}}, "630299": {"Reino Unido": {"exp": 665.0, "imp": 0}, "India": {"exp": 0, "imp": 1056.0}, "Portugal": {"exp": 0, "imp": 742.0}, "Alemania": {"exp": 0, "imp": 105.0}, "Francia": {"exp": 0, "imp": 6567.0}, "Turquía": {"exp": 0, "imp": 336.0}, "España": {"exp": 0, "imp": 1239.0}, "Vietnam": {"exp": 0, "imp": 56.0}, "Sudáfrica": {"exp": 0, "imp": 3521.0}, "Panamá": {"exp": 0, "imp": 359.0}, "Lituania": {"exp": 0, "imp": 1565.0}, "Italia": {"exp": 0, "imp": 1832.0}, "Estados Unidos": {"exp": 0, "imp": 20485.0}, "China": {"exp": 0, "imp": 9563.0}, "Bélgica": {"exp": 0, "imp": 13343.0}}, "630391": {"Paraguay": {"exp": 32.0, "imp": 0}, "China": {"exp": 0, "imp": 15249.0}, "Brasil": {"exp": 0, "imp": 19280.0}, "Pakistán": {"exp": 0, "imp": 1758.0}, "India": {"exp": 0, "imp": 35530.0}, "Estados Unidos": {"exp": 0, "imp": 542.0}, "Portugal": {"exp": 0, "imp": 2543.0}, "Argentina": {"exp": 0, "imp": 28102.0}, "Bangladesh": {"exp": 0, "imp": 2185.0}, "Camboya": {"exp": 0, "imp": 6173.0}}, "630251": {"Paraguay": {"exp": 215.0, "imp": 3824.0}, "Estados Unidos": {"exp": 350.0, "imp": 75.0}, "Italia": {"exp": 0, "imp": 900.0}, "España": {"exp": 0, "imp": 25853.0}, "Pakistán": {"exp": 0, "imp": 28250.0}, "Francia": {"exp": 0, "imp": 95.0}, "Colombia": {"exp": 0, "imp": 83.0}, "China": {"exp": 0, "imp": 64767.0}, "Portugal": {"exp": 0, "imp": 3649.0}, "Argentina": {"exp": 0, "imp": 14464.0}, "India": {"exp": 0, "imp": 479551.0}, "Brasil": {"exp": 0, "imp": 18484.0}, "Bangladesh": {"exp": 0, "imp": 26488.0}, "Turquía": {"exp": 0, "imp": 6008.0}, "Egipto": {"exp": 0, "imp": 4171.0}, "Dinamarca": {"exp": 0, "imp": 629.0}}, "630291": {"Italia": {"exp": 120.0, "imp": 0}, "Reino Unido": {"exp": 100.0, "imp": 0}, "China": {"exp": 0, "imp": 131243.0}, "Francia": {"exp": 0, "imp": 728.0}, "España": {"exp": 0, "imp": 5115.0}, "Brasil": {"exp": 0, "imp": 1462.0}, "Alemania": {"exp": 0, "imp": 13.0}, "Pakistán": {"exp": 0, "imp": 8791.0}, "India": {"exp": 0, "imp": 63000.0}, "Sudáfrica": {"exp": 0, "imp": 1576.0}, "Suecia": {"exp": 0, "imp": 299.0}, "Turquía": {"exp": 0, "imp": 3221.0}, "Egipto": {"exp": 0, "imp": 754.0}, "Estados Unidos": {"exp": 0, "imp": 2382.0}, "Ecuador": {"exp": 0, "imp": 26.0}, "Portugal": {"exp": 0, "imp": 16161.0}, "Siria": {"exp": 0, "imp": 552.0}, "Argentina": {"exp": 0, "imp": 16897.0}, "Bangladesh": {"exp": 0, "imp": 2984.0}}, "630259": {"España": {"exp": 148.0, "imp": 542.0}, "China": {"exp": 0, "imp": 79141.0}, "Francia": {"exp": 0, "imp": 5622.0}, "Reino Unido": {"exp": 0, "imp": 68.0}, "Brasil": {"exp": 0, "imp": 1360.0}, "Indonesia": {"exp": 0, "imp": 595.0}, "Lituania": {"exp": 0, "imp": 196.0}, "Países Bajos": {"exp": 0, "imp": 122.0}, "Pakistán": {"exp": 0, "imp": 169.0}, "Polonia": {"exp": 0, "imp": 373.0}, "India": {"exp": 0, "imp": 74827.0}, "Vietnam": {"exp": 0, "imp": 643.0}, "Estados Unidos": {"exp": 0, "imp": 1083.0}, "Ecuador": {"exp": 0, "imp": 35.0}, "Portugal": {"exp": 0, "imp": 668.0}, "Argentina": {"exp": 0, "imp": 76.0}, "Bangladesh": {"exp": 0, "imp": 9070.0}, "Italia": {"exp": 0, "imp": 11152.0}, "Bélgica": {"exp": 0, "imp": 2112.0}, "Camboya": {"exp": 0, "imp": 691.0}}, "630622": {"Argentina": {"exp": 1158.0, "imp": 8458.0}, "Paraguay": {"exp": 13570.0, "imp": 0}, "China": {"exp": 0, "imp": 2223731.0}, "Brasil": {"exp": 0, "imp": 138.0}, "Colombia": {"exp": 0, "imp": 3417.0}, "Australia": {"exp": 0, "imp": 1248.0}, "Bangladesh": {"exp": 0, "imp": 67895.0}, "Suiza": {"exp": 0, "imp": 44.0}, "Hong Kong": {"exp": 0, "imp": 61710.0}, "Estados Unidos": {"exp": 0, "imp": 27643.0}, "Reino Unido": {"exp": 0, "imp": 250.0}, "Irlanda": {"exp": 0, "imp": 329.0}, "Vietnam": {"exp": 0, "imp": 46867.0}}, "630229": {"Argentina": {"exp": 195.0, "imp": 22.0}, "China": {"exp": 0, "imp": 87928.0}, "España": {"exp": 0, "imp": 4494.0}, "Brasil": {"exp": 0, "imp": 5.0}, "Pakistán": {"exp": 0, "imp": 19.0}, "India": {"exp": 0, "imp": 17396.0}, "Suecia": {"exp": 0, "imp": 3162.0}, "Turquía": {"exp": 0, "imp": 1567.0}, "Estados Unidos": {"exp": 0, "imp": 407.0}, "Portugal": {"exp": 0, "imp": 74.0}}, "630411": {"Estados Unidos": {"exp": 0, "imp": 31.0}, "Portugal": {"exp": 0, "imp": 318.0}, "China": {"exp": 0, "imp": 17051.0}}, "630420": {"China": {"exp": 0, "imp": 2475.0}, "Estados Unidos": {"exp": 0, "imp": 34.0}}, "630510": {"China": {"exp": 0, "imp": 6176.0}, "Brasil": {"exp": 0, "imp": 390.0}, "India": {"exp": 0, "imp": 14425.0}, "Argentina": {"exp": 0, "imp": 75.0}}, "630630": {"China": {"exp": 0, "imp": 24783.0}, "Chequia": {"exp": 0, "imp": 8258.0}, "Francia": {"exp": 0, "imp": 2108.0}, "Alemania": {"exp": 0, "imp": 16036.0}, "Polonia": {"exp": 0, "imp": 7316.0}}, "630800": {"China": {"exp": 0, "imp": 3380.0}, "Brasil": {"exp": 0, "imp": 2385.0}}, "630499": {"España": {"exp": 0, "imp": 3049.0}, "Países Bajos": {"exp": 0, "imp": 1357.0}, "Lituania": {"exp": 0, "imp": 755.0}, "Francia": {"exp": 0, "imp": 8212.0}, "China": {"exp": 0, "imp": 180052.0}, "Portugal": {"exp": 0, "imp": 11208.0}, "Argentina": {"exp": 0, "imp": 12966.0}, "India": {"exp": 0, "imp": 115662.0}, "Camboya": {"exp": 0, "imp": 4032.0}, "Brasil": {"exp": 0, "imp": 10997.0}, "Bangladesh": {"exp": 0, "imp": 345.0}, "Estados Unidos": {"exp": 0, "imp": 574.0}, "Turquía": {"exp": 0, "imp": 2475.0}}}