{"170199": {"Brasil": {"exp": 117241.0, "imp": 0}, "Uruguay": {"exp": 297804.21, "imp": 186384.87}, "Estados Unidos": {"exp": 61362870.63, "imp": 23905.72}, "Alemania": {"exp": 6593545.0, "imp": 17590.15}, "Canadá": {"exp": 596568.0, "imp": 0}, "Países Bajos": {"exp": 2769656.7, "imp": 0}, "Suiza": {"exp": 1892675.0, "imp": 0}, "Francia": {"exp": 643088.8999999999, "imp": 35222.0}, "Italia": {"exp": 442300.0, "imp": 0}, "China": {"exp": 487227.0, "imp": 0}, "Bélgica": {"exp": 1564193.3900000001, "imp": 0}, "Australia": {"exp": 257245.0, "imp": 0}, "Reino Unido": {"exp": 70400.0, "imp": 0}, "Lituania": {"exp": 836000.0, "imp": 0}, "España": {"exp": 73.0, "imp": 72.36}, "Ecuador": {"exp": 0, "imp": 9.03}, "Colombia": {"exp": 0, "imp": 7.28}, "Argentina": {"exp": 0, "imp": 167114.6}, "Filipinas": {"exp": 18460.0, "imp": 0}, "México": {"exp": 116130.0, "imp": 0}, "Ghana": {"exp": 18750.0, "imp": 0}, "Hong Kong": {"exp": 2702.41, "imp": 0}, "Nueva Zelanda": {"exp": 84000.0, "imp": 0}, "Perú": {"exp": 37964.0, "imp": 0}}, "170211": {"Bolivia": {"exp": 8138.5, "imp": 0}, "Uruguay": {"exp": 43712.0, "imp": 0}, "Países Bajos": {"exp": 0, "imp": 339763.51}, "India": {"exp": 0, "imp": 18200.0}, "Alemania": {"exp": 0, "imp": 157391.76}, "China": {"exp": 0, "imp": 6109.0}}, "170114": {"Uruguay": {"exp": 78524.0, "imp": 0}, "Estados Unidos": {"exp": 254463290.10000002, "imp": 17250.99}, "Argentina": {"exp": 2054263.0, "imp": 0}, "Chile": {"exp": 77690.0, "imp": 0}, "España": {"exp": 682894.13, "imp": 0}, "Australia": {"exp": 569370.0, "imp": 0}, "Austria": {"exp": 118980.0, "imp": 0}, "Bélgica": {"exp": 9209822.33, "imp": 0}, "Canadá": {"exp": 9368853.75, "imp": 0}, "Benin": {"exp": 22000.0, "imp": 0}, "Rep. Dominicana": {"exp": 87800.0, "imp": 0}, "Ecuador": {"exp": 44300.0, "imp": 0}, "Francia": {"exp": 11528650.129999999, "imp": 0}, "Alemania": {"exp": 30661504.93, "imp": 0}, "Italia": {"exp": 11660080.379999999, "imp": 0}, "Japón": {"exp": 100200.0, "imp": 0}, "Corea del Sur": {"exp": 2435332.0, "imp": 0}, "México": {"exp": 629070.0, "imp": 0}, "Países Bajos": {"exp": 16554368.5, "imp": 0}, "Nueva Zelanda": {"exp": 1238184.0, "imp": 0}, "Perú": {"exp": 2775350.0, "imp": 0}, "Filipinas": {"exp": 160820.0, "imp": 0}, "Arabia Saudita": {"exp": 171950.0, "imp": 0}, "Suecia": {"exp": 41297538.0, "imp": 0}, "Suiza": {"exp": 30725985.0, "imp": 0}, "Reino Unido": {"exp": 777468.5, "imp": 0}, "Costa Rica": {"exp": 338030.0, "imp": 0}, "Túnez": {"exp": 1121850.0, "imp": 0}, "Vietnam": {"exp": 10675.0, "imp": 0}, "Malasia": {"exp": 396600.0, "imp": 0}, "Portugal": {"exp": 219000.0, "imp": 0}, "Grecia": {"exp": 17790.0, "imp": 0}, "Noruega": {"exp": 101250.0, "imp": 0}, "China": {"exp": 75675.0, "imp": 0}, "Letonia": {"exp": 19000.0, "imp": 0}, "Lituania": {"exp": 970000.0, "imp": 0}, "Brasil": {"exp": 18850.0, "imp": 0}, "Eslovenia": {"exp": 32368.0, "imp": 0}, "Ghana": {"exp": 149192.0, "imp": 0}, "Bolivia": {"exp": 16250.0, "imp": 0}, "Egipto": {"exp": 80.0, "imp": 0}}, "170230": {"Estados Unidos": {"exp": 31356.0, "imp": 403.91}, "Corea del Sur": {"exp": 0, "imp": 2001.99}, "Francia": {"exp": 0, "imp": 25957.03}, "India": {"exp": 0, "imp": 103259.0}, "España": {"exp": 0, "imp": 168.19}, "Argentina": {"exp": 0, "imp": 191487.48}, "China": {"exp": 0, "imp": 209262.74}, "Brasil": {"exp": 0, "imp": 482656.48}, "Alemania": {"exp": 0, "imp": 26.0}, "Uruguay": {"exp": 92.25, "imp": 0}}, "170310": {"Estados Unidos": {"exp": 4920027.96, "imp": 0}, "España": {"exp": 272864.74, "imp": 0}, "Australia": {"exp": 111703.0, "imp": 0}, "Austria": {"exp": 13500.0, "imp": 0}, "Canadá": {"exp": 114551.0, "imp": 0}, "Chequia": {"exp": 119352.1, "imp": 0}, "Alemania": {"exp": 7127192.27, "imp": 0}, "Italia": {"exp": 345421.9, "imp": 0}, "Japón": {"exp": 88329.0, "imp": 0}, "Países Bajos": {"exp": 3027609.5, "imp": 0}, "Suiza": {"exp": 82977.0, "imp": 0}, "Reino Unido": {"exp": 78365.0, "imp": 0}, "Malasia": {"exp": 45846.0, "imp": 0}, "Nueva Zelanda": {"exp": 28888.08, "imp": 0}, "Suecia": {"exp": 11468.0, "imp": 0}, "Madagascar": {"exp": 21817.0, "imp": 0}, "Colombia": {"exp": 54054.0, "imp": 0}, "Francia": {"exp": 196251.0, "imp": 0}, "Chile": {"exp": 30280.0, "imp": 0}, "Uruguay": {"exp": 12620.0, "imp": 63050.53}, "Dinamarca": {"exp": 2700.0, "imp": 0}, "Brasil": {"exp": 0, "imp": 428.91}, "Irlanda": {"exp": 9032.8, "imp": 0}, "Argentina": {"exp": 28800.0, "imp": 0}}, "170290": {"Canadá": {"exp": 3089.0, "imp": 0}, "España": {"exp": 10240.0, "imp": 0}, "Argentina": {"exp": 23036.0, "imp": 205606.18}, "Uruguay": {"exp": 4477.75, "imp": 28586.14}, "Chile": {"exp": 189141.88, "imp": 1167.33}, "Finlandia": {"exp": 0, "imp": 501.55}, "Japón": {"exp": 0, "imp": 4147.1}, "Estados Unidos": {"exp": 0, "imp": 26521.02}, "Reino Unido": {"exp": 0, "imp": 620.87}, "Corea del Sur": {"exp": 0, "imp": 303.0}, "Francia": {"exp": 0, "imp": 70.32}, "Israel": {"exp": 0, "imp": 78.08}, "Alemania": {"exp": 0, "imp": 5191.64}, "China": {"exp": 0, "imp": 14879.41}, "Brasil": {"exp": 0, "imp": 425316.72}}, "170490": {"Canadá": {"exp": 74938.5, "imp": 0}, "Uruguay": {"exp": 9796.0, "imp": 469.0}, "Brasil": {"exp": 111460.1, "imp": 15277654.38}, "Costa Rica": {"exp": 22060.0, "imp": 0}, "Rep. Dominicana": {"exp": 22083.0, "imp": 0}, "Nicaragua": {"exp": 11112.0, "imp": 0}, "Argentina": {"exp": 10227.0, "imp": 6894643.25}, "Bolivia": {"exp": 2448.0, "imp": 0}, "España": {"exp": 564.39, "imp": 55708.97}, "Indonesia": {"exp": 0, "imp": 6875.18}, "Líbano": {"exp": 0, "imp": 2079.57}, "Ecuador": {"exp": 0, "imp": 73520.9}, "Polonia": {"exp": 0, "imp": 44816.6}, "Austria": {"exp": 0, "imp": 21322.88}, "Bélgica": {"exp": 0, "imp": 27486.45}, "Suiza": {"exp": 0, "imp": 54292.98}, "Corea del Sur": {"exp": 0, "imp": 4063.47}, "Francia": {"exp": 0, "imp": 12759.55}, "México": {"exp": 0, "imp": 34201.0}, "Chile": {"exp": 2020.8, "imp": 781216.06}, "Italia": {"exp": 0, "imp": 683.81}, "Alemania": {"exp": 0, "imp": 243317.11}, "Estados Unidos": {"exp": 48837.98, "imp": 96228.07}, "China": {"exp": 0, "imp": 392028.52}, "Países Bajos": {"exp": 1048.0, "imp": 0}}, "170113": {"España": {"exp": 2386.0, "imp": 0}, "Países Bajos": {"exp": 479244.5, "imp": 0}, "Francia": {"exp": 228.0, "imp": 0}, "Chequia": {"exp": 24.3, "imp": 0}, "Canadá": {"exp": 35000.0, "imp": 0}}, "170410": {"Canadá": {"exp": 164.0, "imp": 0}, "Brasil": {"exp": 77968.44, "imp": 2781770.71}, "Costa Rica": {"exp": 4350.0, "imp": 0}, "Rep. Dominicana": {"exp": 4350.0, "imp": 0}, "Nicaragua": {"exp": 3552.0, "imp": 0}, "Bolivia": {"exp": 0, "imp": 7146.0}, "Chile": {"exp": 0, "imp": 35.16}, "España": {"exp": 0, "imp": 997.67}, "Alemania": {"exp": 0, "imp": 40412.69}, "Estados Unidos": {"exp": 0, "imp": 8987.23}, "Argentina": {"exp": 0, "imp": 471425.9}, "China": {"exp": 0, "imp": 120739.87}}, "170219": {"Uruguay": {"exp": 30549.5, "imp": 0}, "Canadá": {"exp": 554.0, "imp": 0}, "Argentina": {"exp": 31442.0, "imp": 0}, "China": {"exp": 0, "imp": 38235.0}, "Estados Unidos": {"exp": 1770.0, "imp": 56583.49}, "Israel": {"exp": 0, "imp": 396.69}, "Nueva Zelanda": {"exp": 0, "imp": 854.43}, "Corea del Sur": {"exp": 0, "imp": 357.8}, "India": {"exp": 0, "imp": 4922.0}, "Alemania": {"exp": 0, "imp": 325190.76}, "Países Bajos": {"exp": 0, "imp": 97.25}, "Brasil": {"exp": 0, "imp": 12.55}}, "170250": {"Finlandia": {"exp": 0, "imp": 501.25}, "Israel": {"exp": 0, "imp": 76.3}}, "170390": {"Emiratos Árabes": {"exp": 0, "imp": 14.51}}, "170260": {"Uruguay": {"exp": 0, "imp": 830.49}, "Corea del Sur": {"exp": 0, "imp": 3244.24}, "Estados Unidos": {"exp": 0, "imp": 20872.97}, "Argentina": {"exp": 0, "imp": 1590049.29}}, "170220": {"Estados Unidos": {"exp": 0, "imp": 8376.26}}}