{"300210": {"Brasil": {"exp": 2062500.0, "imp": 0}, "Bolivia": {"exp": 42220.0, "imp": 0}, "Argentina": {"exp": 55515.0, "imp": 0}, "Colombia": {"exp": 1276853.0, "imp": 0}, "Francia": {"exp": 648192.0, "imp": 0}, "Países Bajos": {"exp": 11.0, "imp": 0}, "Vietnam": {"exp": 22500.0, "imp": 0}}, "300230": {"Brasil": {"exp": 314083.0, "imp": 0}, "Bolivia": {"exp": 1786620.0, "imp": 0}, "Uruguay": {"exp": 12708485.0, "imp": 0}}, "300420": {"Brasil": {"exp": 33376546.720000003, "imp": 2388107.09}, "Bolivia": {"exp": 9943112.83, "imp": 0}, "Uruguay": {"exp": 2240718.5300000003, "imp": 531290.24}, "Estados Unidos": {"exp": 16632.0, "imp": 891979.21}, "Argentina": {"exp": 1933226.3499999999, "imp": 2452124.71}, "Chile": {"exp": 842821.28, "imp": 1065007.23}, "Angola": {"exp": 4736.0, "imp": 0}, "Colombia": {"exp": 1323779.67, "imp": 308379.17}, "Costa Rica": {"exp": 102205.17, "imp": 0}, "Cuba": {"exp": 126413.67, "imp": 0}, "Rep. Dominicana": {"exp": 402683.32000000007, "imp": 0}, "Ecuador": {"exp": 2523816.14, "imp": 149245.73}, "El Salvador": {"exp": 783127.29, "imp": 14264.01}, "Guatemala": {"exp": 418219.36, "imp": 0}, "Honduras": {"exp": 210478.5, "imp": 0}, "Jamaica": {"exp": 2848.0, "imp": 0}, "Kazajistán": {"exp": 7709.0, "imp": 0}, "México": {"exp": 4578305.76, "imp": 18750.57}, "Nicaragua": {"exp": 69739.48000000001, "imp": 0}, "Panamá": {"exp": 523607.15, "imp": 0}, "Perú": {"exp": 4954942.779999999, "imp": 92771.51}, "Saint Lucia": {"exp": 1325.0, "imp": 0}, "Venezuela": {"exp": 1151263.96, "imp": 0}, "Omán": {"exp": 5382.0, "imp": 0}, "Mozambique": {"exp": 23072.0, "imp": 0}, "Belice": {"exp": 48709.0, "imp": 0}, "India": {"exp": 13899.0, "imp": 634813.67}, "Suiza": {"exp": 0, "imp": 137185.78}, "Francia": {"exp": 0, "imp": 219441.46}, "Chipre": {"exp": 0, "imp": 1458.02}, "Grecia": {"exp": 0, "imp": 143829.63}, "Canadá": {"exp": 0, "imp": 8936.0}, "Países Bajos": {"exp": 0, "imp": 495.0}, "Reino Unido": {"exp": 0, "imp": 51297.31}, "Italia": {"exp": 0, "imp": 382400.0}, "España": {"exp": 0, "imp": 84343.79}, "Alemania": {"exp": 0, "imp": 309205.06}, "Turquía": {"exp": 0, "imp": 22.0}, "China": {"exp": 0, "imp": 373240.82}}, "300432": {"Brasil": {"exp": 454.0, "imp": 23449.01}, "Bolivia": {"exp": 1482888.5499999998, "imp": 0}, "Uruguay": {"exp": 1411096.6400000001, "imp": 240519.41}, "Argentina": {"exp": 1182.0, "imp": 1467167.89}, "Angola": {"exp": 5376.0, "imp": 0}, "Cuba": {"exp": 120975.0, "imp": 0}, "Ecuador": {"exp": 49655.27, "imp": 0}, "El Salvador": {"exp": 53431.12, "imp": 886.09}, "Guatemala": {"exp": 226041.78, "imp": 0}, "Honduras": {"exp": 142269.53, "imp": 0}, "Jamaica": {"exp": 3158.0, "imp": 0}, "Nicaragua": {"exp": 4348.0, "imp": 0}, "Perú": {"exp": 572950.16, "imp": 4878.55}, "Saint Lucia": {"exp": 358.0, "imp": 0}, "Rep. Dominicana": {"exp": 290566.52, "imp": 0}, "Haití": {"exp": 1958.0, "imp": 0}, "Chile": {"exp": 187305.45, "imp": 882474.08}, "Jordania": {"exp": 371751.3, "imp": 0}, "Italia": {"exp": 27.0, "imp": 304400.85}, "Mozambique": {"exp": 7393.0, "imp": 0}, "Panamá": {"exp": 143352.13, "imp": 0}, "Turquía": {"exp": 36794.8, "imp": 663.0}, "Venezuela": {"exp": 34516.93, "imp": 0}, "Belice": {"exp": 58308.0, "imp": 0}, "Colombia": {"exp": 0, "imp": 25572.34}, "Reino Unido": {"exp": 0, "imp": 10175.31}, "México": {"exp": 0, "imp": 20865.0}, "India": {"exp": 0, "imp": 348000.0}, "España": {"exp": 0, "imp": 1120915.92}, "Alemania": {"exp": 0, "imp": 13332.35}, "China": {"exp": 0, "imp": 83562.4}}, "300490": {"Brasil": {"exp": 321980.24, "imp": 14326003.5}, "Bolivia": {"exp": 62246359.61, "imp": 69971.5}, "Uruguay": {"exp": 21198565.25, "imp": 7367960.81}, "Chile": {"exp": 28102436.21, "imp": 14959874.75}, "Angola": {"exp": 44041.0, "imp": 0}, "Belice": {"exp": 1931514.5, "imp": 0}, "Colombia": {"exp": 11930285.190000001, "imp": 2316422.4}, "Costa Rica": {"exp": 4483881.14, "imp": 0}, "Cuba": {"exp": 859619.23, "imp": 42750.0}, "Rep. Dominicana": {"exp": 5690335.68, "imp": 696384.51}, "Ecuador": {"exp": 55652922.89, "imp": 544637.67}, "El Salvador": {"exp": 13931522.450000001, "imp": 9824.08}, "Haití": {"exp": 42355.770000000004, "imp": 0}, "Honduras": {"exp": 4958511.53, "imp": 0}, "Jamaica": {"exp": 8542.0, "imp": 0}, "México": {"exp": 30585784.050000004, "imp": 2485538.63}, "Nicaragua": {"exp": 3815712.82, "imp": 0}, "Panamá": {"exp": 23025243.04, "imp": 0}, "Perú": {"exp": 50429190.81, "imp": 909219.03}, "Saint Lucia": {"exp": 2534.0, "imp": 0}, "Emiratos Árabes": {"exp": 720528.8500000001, "imp": 0}, "Venezuela": {"exp": 10616839.79, "imp": 0}, "Argentina": {"exp": 3625188.37, "imp": 25821800.38}, "Dominica": {"exp": 248317.0, "imp": 0}, "Guatemala": {"exp": 15073198.959999999, "imp": 0}, "Azerbaiyán": {"exp": 55358.6, "imp": 0}, "Sri Lanka": {"exp": 1246.0, "imp": 0}, "Georgia": {"exp": 107054.0, "imp": 0}, "Kuwait": {"exp": 184979.38, "imp": 0}, "Líbano": {"exp": 189718.11, "imp": 0}, "Omán": {"exp": 82315.0, "imp": 0}, "Mozambique": {"exp": 135941.0, "imp": 0}, "Italia": {"exp": 7265.0, "imp": 2772145.29}, "Qatar": {"exp": 167540.16, "imp": 0}, "Mauricio": {"exp": 19433.0, "imp": 0}, "Jordania": {"exp": 645216.4, "imp": 0}, "Yemen": {"exp": 180.0, "imp": 0}, "Libia": {"exp": 248640.0, "imp": 0}, "Alemania": {"exp": 1355.23, "imp": 14875251.28}, "China": {"exp": 35785.0, "imp": 2576015.71}, "Vietnam": {"exp": 34750.0, "imp": 0}, "Turquía": {"exp": 93896.4, "imp": 88826.67}, "Bulgaria": {"exp": 52017.0, "imp": 0}, "India": {"exp": 4.0, "imp": 5991761.28}, "Singapur": {"exp": 0, "imp": 155707.0}, "Suecia": {"exp": 0, "imp": 851198.55}, "Noruega": {"exp": 0, "imp": 170141.06}, "Corea del Sur": {"exp": 0, "imp": 259190.06}, "Canadá": {"exp": 0, "imp": 368799.41}, "Austria": {"exp": 0, "imp": 876100.53}, "Estados Unidos": {"exp": 50312.0, "imp": 9101012.38}, "Malasia": {"exp": 0, "imp": 6539.0}, "Dinamarca": {"exp": 0, "imp": 4738179.0}, "Israel": {"exp": 0, "imp": 13.03}, "Eslovenia": {"exp": 0, "imp": 92758.0}, "Rumania": {"exp": 0, "imp": 1056000.0}, "Rusia": {"exp": 0, "imp": 22991.89}, "Nueva Zelanda": {"exp": 0, "imp": 17150.0}, "Marruecos": {"exp": 0, "imp": 361521.37}, "Malta": {"exp": 0, "imp": 13124.88}, "Letonia": {"exp": 0, "imp": 80400.0}, "Irlanda": {"exp": 187.3, "imp": 5849404.83}, "Grecia": {"exp": 0, "imp": 1114781.36}, "Chipre": {"exp": 0, "imp": 4617.06}, "Bangladesh": {"exp": 0, "imp": 591416.63}, "Portugal": {"exp": 0, "imp": 32030.01}, "Polonia": {"exp": 0, "imp": 65554.54}, "Bélgica": {"exp": 0, "imp": 1196736.59}, "Suiza": {"exp": 0, "imp": 10990271.49}, "Países Bajos": {"exp": 0, "imp": 246153.24}, "Japón": {"exp": 0, "imp": 21398.69}, "Reino Unido": {"exp": 0, "imp": 1824138.19}, "Francia": {"exp": 0, "imp": 7265596.8}, "España": {"exp": 0, "imp": 6538985.9}, "Chequia": {"exp": 0, "imp": 9945.0}, "Arabia Saudita": {"exp": 28000.0, "imp": 0}, "Baréin": {"exp": 69769.89, "imp": 0}}, "300120": {"Bolivia": {"exp": 90138.5, "imp": 0}, "El Salvador": {"exp": 7564.2, "imp": 0}, "Honduras": {"exp": 10172.0, "imp": 0}, "Nicaragua": {"exp": 29098.7, "imp": 0}, "Kuwait": {"exp": 146.0, "imp": 0}, "Costa Rica": {"exp": 20.0, "imp": 0}, "Ecuador": {"exp": 1014.0, "imp": 0}, "Brasil": {"exp": 21.0, "imp": 65334.17}, "Francia": {"exp": 10.0, "imp": 0}, "Estados Unidos": {"exp": 20.0, "imp": 0}, "Argentina": {"exp": 0, "imp": 23586.43}}, "300410": {"Bolivia": {"exp": 3951769.3699999996, "imp": 0}, "Costa Rica": {"exp": 3100.0, "imp": 0}, "Rep. Dominicana": {"exp": 131523.05, "imp": 0}, "El Salvador": {"exp": 544033.1599999999, "imp": 2829.1}, "Guatemala": {"exp": 1061062.69, "imp": 0}, "Honduras": {"exp": 427382.0, "imp": 0}, "México": {"exp": 104464.0, "imp": 0}, "Nicaragua": {"exp": 433140.35, "imp": 0}, "Panamá": {"exp": 116279.1, "imp": 0}, "Perú": {"exp": 283493.0, "imp": 0}, "Colombia": {"exp": 53915.0, "imp": 16096.34}, "Cuba": {"exp": 85587.0, "imp": 0}, "Belice": {"exp": 7631.0, "imp": 0}, "China": {"exp": 0, "imp": 38555.83}, "Eslovenia": {"exp": 0, "imp": 46860.26}, "Países Bajos": {"exp": 0, "imp": 17853.07}, "Uruguay": {"exp": 0, "imp": 177565.81}, "Reino Unido": {"exp": 0, "imp": 14705.26}, "Chile": {"exp": 0, "imp": 860222.72}, "India": {"exp": 0, "imp": 367.56}, "Italia": {"exp": 0, "imp": 36793.44}, "España": {"exp": 0, "imp": 34797.58}, "Argentina": {"exp": 0, "imp": 956387.4}, "Brasil": {"exp": 0, "imp": 668046.48}}, "300439": {"Bolivia": {"exp": 3574085.7800000003, "imp": 0}, "Chile": {"exp": 17024.0, "imp": 507284.71}, "Angola": {"exp": 6482.0, "imp": 0}, "Costa Rica": {"exp": 25456.0, "imp": 0}, "Cuba": {"exp": 11289.0, "imp": 0}, "Rep. Dominicana": {"exp": 120083.9, "imp": 0}, "Ecuador": {"exp": 247660.75999999998, "imp": 0}, "Guatemala": {"exp": 59174.0, "imp": 0}, "Honduras": {"exp": 56616.0, "imp": 0}, "Nicaragua": {"exp": 24820.26, "imp": 0}, "Panamá": {"exp": 8409.0, "imp": 0}, "Perú": {"exp": 6328856.830000001, "imp": 0}, "Belice": {"exp": 9710.0, "imp": 0}, "El Salvador": {"exp": 5132.0, "imp": 0}, "México": {"exp": 48510.0, "imp": 10679.94}, "Uruguay": {"exp": 112780.88, "imp": 239456.18}, "Colombia": {"exp": 19000.0, "imp": 37439.61}, "Venezuela": {"exp": 88944.5, "imp": 0}, "Corea del Sur": {"exp": 0, "imp": 18053.96}, "Irlanda": {"exp": 0, "imp": 122466.02}, "Austria": {"exp": 0, "imp": 472576.7}, "Suiza": {"exp": 0, "imp": 88099.7}, "Canadá": {"exp": 0, "imp": 262500.0}, "Países Bajos": {"exp": 0, "imp": 30331.91}, "Francia": {"exp": 0, "imp": 132690.27}, "India": {"exp": 0, "imp": 315056.68}, "Italia": {"exp": 0, "imp": 83103.0}, "España": {"exp": 0, "imp": 569580.65}, "Alemania": {"exp": 0, "imp": 1264335.43}, "Estados Unidos": {"exp": 0, "imp": 964967.77}, "Argentina": {"exp": 0, "imp": 6929381.47}, "China": {"exp": 0, "imp": 360833.03}, "Brasil": {"exp": 0, "imp": 1121229.07}}, "300440": {"Bolivia": {"exp": 5253.0, "imp": 0}, "Uruguay": {"exp": 17675.0, "imp": 0}, "Cuba": {"exp": 2400.0, "imp": 0}, "Ecuador": {"exp": 768.0, "imp": 0}, "Guatemala": {"exp": 507.0, "imp": 0}, "Haití": {"exp": 64.0, "imp": 0}, "Honduras": {"exp": 307.0, "imp": 0}, "Jamaica": {"exp": 90.0, "imp": 0}, "Saint Lucia": {"exp": 92.0, "imp": 0}}, "300450": {"Bolivia": {"exp": 6934922.86, "imp": 0}, "Uruguay": {"exp": 1215418.58, "imp": 1506183.73}, "Chile": {"exp": 179788.0, "imp": 557970.17}, "Angola": {"exp": 158.0, "imp": 0}, "Costa Rica": {"exp": 20867.0, "imp": 0}, "Rep. Dominicana": {"exp": 238680.62, "imp": 0}, "El Salvador": {"exp": 48155.04, "imp": 8186.8}, "Guatemala": {"exp": 138064.89, "imp": 0}, "Honduras": {"exp": 203988.64, "imp": 0}, "Nicaragua": {"exp": 353245.24, "imp": 0}, "Panamá": {"exp": 13711.0, "imp": 0}, "Perú": {"exp": 2668522.94, "imp": 81275.12}, "Venezuela": {"exp": 49553.0, "imp": 0}, "Sri Lanka": {"exp": 360.0, "imp": 0}, "Cuba": {"exp": 2768.0, "imp": 0}, "Omán": {"exp": 7290.0, "imp": 0}, "Emiratos Árabes": {"exp": 4980.0, "imp": 0}, "Mozambique": {"exp": 8132.0, "imp": 0}, "Kuwait": {"exp": 10100.0, "imp": 0}, "Ecuador": {"exp": 903076.62, "imp": 41148.39}, "Qatar": {"exp": 878.0, "imp": 0}, "Belice": {"exp": 29547.0, "imp": 0}, "Turquía": {"exp": 34037.6, "imp": 0}, "Polonia": {"exp": 0, "imp": 33.8}, "Austria": {"exp": 0, "imp": 5754.22}, "Colombia": {"exp": 0, "imp": 50640.0}, "Reino Unido": {"exp": 0, "imp": 50798.23}, "Francia": {"exp": 0, "imp": 75752.81}, "México": {"exp": 0, "imp": 7134.29}, "India": {"exp": 0, "imp": 243747.6}, "España": {"exp": 0, "imp": 51843.02}, "Italia": {"exp": 0, "imp": 10.59}, "Alemania": {"exp": 0, "imp": 302652.71}, "Estados Unidos": {"exp": 0, "imp": 17332.55}, "Argentina": {"exp": 0, "imp": 4491583.21}, "Suiza": {"exp": 0, "imp": 267.18}, "Brasil": {"exp": 0, "imp": 663255.8}}, "300590": {"Uruguay": {"exp": 583311.07, "imp": 37722.6}, "Estados Unidos": {"exp": 8.0, "imp": 202341.11}, "Brasil": {"exp": 605326.9299999999, "imp": 339443.0}, "Dinamarca": {"exp": 0, "imp": 15651.7}, "Rep. Dominicana": {"exp": 0, "imp": 25103.27}, "Polonia": {"exp": 0, "imp": 3867.23}, "Bélgica": {"exp": 0, "imp": 8123.57}, "Países Bajos": {"exp": 0, "imp": 178.0}, "Turquía": {"exp": 0, "imp": 725.51}, "Francia": {"exp": 0, "imp": 44556.0}, "México": {"exp": 0, "imp": 131174.23}, "India": {"exp": 0, "imp": 29106.71}, "Italia": {"exp": 0, "imp": 40519.07}, "Alemania": {"exp": 0, "imp": 5679.41}, "Argentina": {"exp": 0, "imp": 52146.57}, "Perú": {"exp": 0, "imp": 5778.28}, "China": {"exp": 0, "imp": 810770.4}, "Canadá": {"exp": 0, "imp": 67.0}}, "300340": {"Suiza": {"exp": 71293.0, "imp": 0}}, "300220": {"Canadá": {"exp": 220.0, "imp": 0}, "Argentina": {"exp": 36440.0, "imp": 0}}, "300510": {"Perú": {"exp": 18738.0, "imp": 0}, "Bolivia": {"exp": 6948.0, "imp": 0}, "Alemania": {"exp": 2146.0, "imp": 213953.8}, "Irlanda": {"exp": 58.26, "imp": 67227.8}, "Suecia": {"exp": 0, "imp": 18665.24}, "Sudáfrica": {"exp": 0, "imp": 26862.0}, "Egipto": {"exp": 0, "imp": 5022.0}, "Bélgica": {"exp": 0, "imp": 144408.0}, "Canadá": {"exp": 0, "imp": 34372.01}, "Colombia": {"exp": 0, "imp": 108150.71}, "Reino Unido": {"exp": 0, "imp": 26656.72}, "Hong Kong": {"exp": 0, "imp": 2.51}, "Francia": {"exp": 0, "imp": 588518.99}, "Chile": {"exp": 0, "imp": 196.95}, "Italia": {"exp": 0, "imp": 1586.71}, "Estados Unidos": {"exp": 0, "imp": 263300.2}, "Argentina": {"exp": 0, "imp": 145115.91}, "China": {"exp": 0, "imp": 258037.85}, "Brasil": {"exp": 576012.27, "imp": 300132.67}, "Uruguay": {"exp": 6492.35, "imp": 0}}, "300640": {"Perú": {"exp": 20484.010000000002, "imp": 0}, "Bolivia": {"exp": 7493.0, "imp": 0}, "Turquía": {"exp": 168709.55, "imp": 0}, "Estados Unidos": {"exp": 0, "imp": 106372.83}, "Australia": {"exp": 0, "imp": 24786.15}, "Austria": {"exp": 0, "imp": 96099.04}, "Suiza": {"exp": 0, "imp": 76165.04}, "Japón": {"exp": 0, "imp": 71623.04}, "Corea del Sur": {"exp": 0, "imp": 42560.87}, "Francia": {"exp": 0, "imp": 8638.04}, "México": {"exp": 0, "imp": 1115.88}, "Italia": {"exp": 0, "imp": 12826.01}, "Alemania": {"exp": 0, "imp": 107220.87}, "Argentina": {"exp": 0, "imp": 45216.84}, "Brasil": {"exp": 0, "imp": 243780.99}}, "300290": {"Bolivia": {"exp": 975.0, "imp": 0}, "Brasil": {"exp": 16.75, "imp": 1898796.77}, "Belice": {"exp": 78874.0, "imp": 0}, "Colombia": {"exp": 50040.2, "imp": 80803.34}, "Rep. Dominicana": {"exp": 11507.0, "imp": 0}, "Alemania": {"exp": 15.0, "imp": 573944.4}, "Japón": {"exp": 30.0, "imp": 0}, "Chile": {"exp": 3640.0, "imp": 480.06}, "Corea del Sur": {"exp": 0, "imp": 14310.0}, "Italia": {"exp": 0, "imp": 519906.17}, "China": {"exp": 0, "imp": 6793.02}, "Estados Unidos": {"exp": 554.93, "imp": 1995480.81}, "Dinamarca": {"exp": 0, "imp": 285817.44}, "Ecuador": {"exp": 0, "imp": 35013.88}, "Uruguay": {"exp": 0, "imp": 104477.4}, "Reino Unido": {"exp": 11.03, "imp": 538.93}, "Francia": {"exp": 0, "imp": 126206.28}, "España": {"exp": 0, "imp": 273612.64}, "India": {"exp": 0, "imp": 80.11}, "Argentina": {"exp": 0, "imp": 4109889.87}, "Dominica": {"exp": 25120.0, "imp": 0}, "México": {"exp": 39075.0, "imp": 0}}, "300320": {"Brasil": {"exp": 459.0, "imp": 0}, "India": {"exp": 0, "imp": 143140.44}, "China": {"exp": 0, "imp": 497029.73}}, "300349": {"Brasil": {"exp": 2306.0, "imp": 71949.0}}, "300190": {"Estados Unidos": {"exp": 2525.0, "imp": 365.71}, "Perú": {"exp": 80.0, "imp": 0}, "Alemania": {"exp": 35.0, "imp": 24.18}, "Argentina": {"exp": 30.0, "imp": 11760.0}, "Chile": {"exp": 100.0, "imp": 852.88}, "Países Bajos": {"exp": 150.0, "imp": 0}, "Belice": {"exp": 11445.0, "imp": 0}, "Canadá": {"exp": 10.0, "imp": 0}, "Bélgica": {"exp": 10.0, "imp": 0}, "España": {"exp": 10.0, "imp": 167.41}, "Brasil": {"exp": 21.0, "imp": 10323.25}, "India": {"exp": 1000.0, "imp": 470.27}, "Malasia": {"exp": 0, "imp": 103.0}, "Colombia": {"exp": 0, "imp": 4.51}, "Japón": {"exp": 0, "imp": 78.63}, "Uruguay": {"exp": 0, "imp": 12.8}, "Reino Unido": {"exp": 0, "imp": 85.31}, "Francia": {"exp": 0, "imp": 4.23}, "México": {"exp": 0, "imp": 567.55}, "China": {"exp": 0, "imp": 638408.53}, "Corea del Sur": {"exp": 50.0, "imp": 0}}, "300390": {"Brasil": {"exp": 20323.0, "imp": 163588.38}, "Bolivia": {"exp": 20373.57, "imp": 0}, "Argentina": {"exp": 25.0, "imp": 54604.53}, "Chile": {"exp": 9.0, "imp": 0}, "México": {"exp": 10.0, "imp": 0}, "Belice": {"exp": 1554.0, "imp": 0}, "India": {"exp": 0, "imp": 3580674.1}, "Estados Unidos": {"exp": 0, "imp": 149069.83}, "Dinamarca": {"exp": 0, "imp": 13283.2}, "Austria": {"exp": 0, "imp": 29993.0}, "Corea del Sur": {"exp": 0, "imp": 113009.0}, "Francia": {"exp": 0, "imp": 49972.65}, "Italia": {"exp": 0, "imp": 86999.1}, "China": {"exp": 0, "imp": 499631.99}}, "300441": {"Perú": {"exp": 320.0, "imp": 0}, "Uruguay": {"exp": 1188.0, "imp": 0}, "Chile": {"exp": 0, "imp": 1455796.42}, "Brasil": {"exp": 0, "imp": 16554.58}}, "300212": {"Perú": {"exp": 46350.0, "imp": 0}, "Colombia": {"exp": 10741332.0, "imp": 1739237.96}, "Filipinas": {"exp": 84600.0, "imp": 0}, "Francia": {"exp": 8431132.0, "imp": 314449.23}, "Argentina": {"exp": 1337020.75, "imp": 829288.02}, "Brasil": {"exp": 5001388.5, "imp": 17967.11}, "Malasia": {"exp": 284654.0, "imp": 0}, "México": {"exp": 142911.5, "imp": 0}, "Alemania": {"exp": 2072519.1, "imp": 156198.89}, "Estados Unidos": {"exp": 376.0, "imp": 740813.78}, "Uruguay": {"exp": 5680895.2, "imp": 43351.17}, "Bolivia": {"exp": 67853.0, "imp": 1523527.3}, "Vietnam": {"exp": 1295897.0, "imp": 0}, "Corea del Sur": {"exp": 0, "imp": 308412.1}, "Suecia": {"exp": 0, "imp": 1066318.24}, "Dinamarca": {"exp": 0, "imp": 183600.0}, "Israel": {"exp": 0, "imp": 29204.16}, "Nueva Zelanda": {"exp": 0, "imp": 84880.0}, "Nicaragua": {"exp": 0, "imp": 183.79}, "Irlanda": {"exp": 0, "imp": 379240.87}, "Panamá": {"exp": 0, "imp": 4000.0}, "Austria": {"exp": 0, "imp": 1143097.46}, "Suiza": {"exp": 0, "imp": 2697348.67}, "Países Bajos": {"exp": 0, "imp": 1304093.92}, "Reino Unido": {"exp": 462308.46, "imp": 770281.94}, "India": {"exp": 0, "imp": 699399.16}, "Italia": {"exp": 0, "imp": 1708137.0}, "España": {"exp": 10.0, "imp": 818096.73}, "Chile": {"exp": 10.0, "imp": 0}}, "300215": {"Venezuela": {"exp": 66300.0, "imp": 0}, "Argentina": {"exp": 88193.0, "imp": 7189794.44}, "Bolivia": {"exp": 22990.42, "imp": 0}, "Turquía": {"exp": 0, "imp": 635499.99}, "Brasil": {"exp": 0, "imp": 404173.85}, "Luxemburgo": {"exp": 0, "imp": 6392.0}, "Hungría": {"exp": 0, "imp": 3943.0}, "Irlanda": {"exp": 0, "imp": 7963749.06}, "Austria": {"exp": 0, "imp": 33656.27}, "Bélgica": {"exp": 0, "imp": 378880.0}, "Suiza": {"exp": 0, "imp": 11056389.08}, "Japón": {"exp": 0, "imp": 2657478.14}, "Uruguay": {"exp": 0, "imp": 11872.88}, "Reino Unido": {"exp": 0, "imp": 317331.97}, "Corea del Sur": {"exp": 0, "imp": 1333189.94}, "India": {"exp": 0, "imp": 1039029.24}, "Italia": {"exp": 0, "imp": 930327.5}, "España": {"exp": 0, "imp": 29872.26}, "Alemania": {"exp": 0, "imp": 33037111.87}, "Estados Unidos": {"exp": 4680.0, "imp": 2713489.87}, "China": {"exp": 0, "imp": 690.0}, "Francia": {"exp": 0, "imp": 1988.0}, "Israel": {"exp": 0, "imp": 279.0}, "Panamá": {"exp": 40250.0, "imp": 0}, "Dinamarca": {"exp": 20.0, "imp": 0}}, "300449": {"Bolivia": {"exp": 218778.78, "imp": 0}, "Brasil": {"exp": 641187.0, "imp": 138399.71}, "Guatemala": {"exp": 1221716.3, "imp": 0}, "Georgia": {"exp": 50125.0, "imp": 0}, "Uruguay": {"exp": 152312.5, "imp": 47858.78}, "Argentina": {"exp": 2657.86, "imp": 398493.77}, "Belice": {"exp": 14752.0, "imp": 0}, "Perú": {"exp": 0, "imp": 1987.26}, "Colombia": {"exp": 0, "imp": 94629.54}, "Francia": {"exp": 0, "imp": 27815.68}, "México": {"exp": 0, "imp": 187120.0}, "Chile": {"exp": 0, "imp": 329969.73}, "Italia": {"exp": 0, "imp": 82560.0}, "Alemania": {"exp": 0, "imp": 376679.57}, "Austria": {"exp": 0, "imp": 2834.0}, "China": {"exp": 0, "imp": 2768.77}, "Ecuador": {"exp": 100624.43, "imp": 0}, "Rep. Dominicana": {"exp": 12750.0, "imp": 0}, "El Salvador": {"exp": 6670.3, "imp": 0}, "Honduras": {"exp": 2221.8, "imp": 0}}, "300610": {"España": {"exp": 79581.0, "imp": 117719.29}, "Perú": {"exp": 0, "imp": 278128.61}, "Egipto": {"exp": 0, "imp": 1989.0}, "Chipre": {"exp": 0, "imp": 21149.41}, "Rep. Dominicana": {"exp": 0, "imp": 114805.11}, "Países Bajos": {"exp": 0, "imp": 54435.99}, "Uruguay": {"exp": 0, "imp": 33.71}, "Corea del Sur": {"exp": 0, "imp": 27859.61}, "México": {"exp": 0, "imp": 44012.51}, "India": {"exp": 0, "imp": 190648.51}, "Italia": {"exp": 0, "imp": 20243.88}, "Alemania": {"exp": 0, "imp": 4366.38}, "Estados Unidos": {"exp": 0, "imp": 480771.25}, "Argentina": {"exp": 0, "imp": 32341.33}, "China": {"exp": 0, "imp": 527.52}, "Brasil": {"exp": 0, "imp": 440779.36}, "Canadá": {"exp": 0, "imp": 49.0}}, "300442": {"Jordania": {"exp": 4150.0, "imp": 0}, "Venezuela": {"exp": 7168.0, "imp": 0}, "Rep. Dominicana": {"exp": 4.0, "imp": 0}, "Bolivia": {"exp": 459859.93, "imp": 0}, "Colombia": {"exp": 0, "imp": 13965.0}, "Argentina": {"exp": 0, "imp": 225555.14}}, "300630": {"Uruguay": {"exp": 44000.0, "imp": 0}, "Canadá": {"exp": 0, "imp": 12658.5}, "Italia": {"exp": 0, "imp": 276114.52}, "España": {"exp": 0, "imp": 6653.15}, "Francia": {"exp": 0, "imp": 10739.0}, "Alemania": {"exp": 0, "imp": 309282.15}, "Argentina": {"exp": 0, "imp": 40284.79}, "China": {"exp": 0, "imp": 673.0}, "Brasil": {"exp": 0, "imp": 505020.0}}, "300431": {"Uruguay": {"exp": 4462.03, "imp": 0}, "Argentina": {"exp": 89080.0, "imp": 0}, "Malasia": {"exp": 0, "imp": 63250.48}, "Dinamarca": {"exp": 0, "imp": 2849639.1}, "Ucrania": {"exp": 0, "imp": 17123.86}, "Polonia": {"exp": 0, "imp": 216090.18}, "Francia": {"exp": 0, "imp": 500998.84}, "México": {"exp": 0, "imp": 133994.64}, "India": {"exp": 0, "imp": 314040.0}, "Italia": {"exp": 0, "imp": 267209.32}, "Alemania": {"exp": 0, "imp": 5587967.53}, "Estados Unidos": {"exp": 0, "imp": 306955.52}, "China": {"exp": 0, "imp": 97504.0}}, "300660": {"Ecuador": {"exp": 274860.58, "imp": 0}, "Bolivia": {"exp": 132221.65, "imp": 0}, "Belice": {"exp": 741.0, "imp": 0}, "Alemania": {"exp": 2582.0, "imp": 364774.58}, "Indonesia": {"exp": 0, "imp": 85308.9}, "Finlandia": {"exp": 0, "imp": 184153.08}, "Bangladesh": {"exp": 0, "imp": 16787.0}, "Bélgica": {"exp": 0, "imp": 101836.0}, "Países Bajos": {"exp": 0, "imp": 190465.0}, "Colombia": {"exp": 0, "imp": 124796.72}, "Uruguay": {"exp": 1080.0, "imp": 1133296.88}, "México": {"exp": 0, "imp": 323007.5}, "Chile": {"exp": 26705.0, "imp": 847718.3}, "India": {"exp": 0, "imp": 763856.88}, "España": {"exp": 0, "imp": 453786.21}, "Argentina": {"exp": 0, "imp": 253509.84}, "Brasil": {"exp": 0, "imp": 1499038.35}}, "300460": {"Belice": {"exp": 615.0, "imp": 0}, "Chipre": {"exp": 0, "imp": 1580.0}, "India": {"exp": 0, "imp": 791.38}}, "300693": {"Guatemala": {"exp": 13.05, "imp": 0}, "Argentina": {"exp": 17.5, "imp": 0}, "Chile": {"exp": 89.75, "imp": 0}, "Brasil": {"exp": 26980.190000000002, "imp": 0}, "Alemania": {"exp": 6074.280000000001, "imp": 0}, "Italia": {"exp": 439.64, "imp": 0}, "India": {"exp": 33286.18, "imp": 0}, "México": {"exp": 1.7, "imp": 0}, "España": {"exp": 10599.44, "imp": 0}}, "300213": {"Panamá": {"exp": 6329.0, "imp": 0}, "Suiza": {"exp": 0, "imp": 90943.6}, "Reino Unido": {"exp": 0, "imp": 397421.12}, "Francia": {"exp": 0, "imp": 334600.12}, "España": {"exp": 0, "imp": 8142.78}, "Italia": {"exp": 0, "imp": 26705.14}}, "300241": {"Chile": {"exp": 5438.0, "imp": 0}, "Rusia": {"exp": 0, "imp": 7265895.81}, "Irlanda": {"exp": 0, "imp": 108000.01}, "Bélgica": {"exp": 0, "imp": 20057530.6}, "Canadá": {"exp": 0, "imp": 3145778.48}, "Países Bajos": {"exp": 0, "imp": 669696.45}, "Reino Unido": {"exp": 0, "imp": 1033802.0}, "Corea del Sur": {"exp": 0, "imp": 38796.0}, "Francia": {"exp": 0, "imp": 6333486.46}, "India": {"exp": 0, "imp": 683265.99}, "España": {"exp": 0, "imp": 3128550.15}, "Alemania": {"exp": 0, "imp": 5657283.09}, "Estados Unidos": {"exp": 0, "imp": 30905132.99}, "Argentina": {"exp": 0, "imp": 12118076.84}, "China": {"exp": 0, "imp": 5204683.17}, "Brasil": {"exp": 0, "imp": 224076.6}}, "300242": {"Uruguay": {"exp": 3112800.0, "imp": 1828919.3}, "Países Bajos": {"exp": 0, "imp": 226555.15}, "Hungría": {"exp": 0, "imp": 419439.27}, "Francia": {"exp": 0, "imp": 54603.78}, "España": {"exp": 0, "imp": 453490.95}, "Estados Unidos": {"exp": 0, "imp": 2493461.6}, "Argentina": {"exp": 0, "imp": 1665060.87}, "Brasil": {"exp": 0, "imp": 2868861.26}, "Bolivia": {"exp": 28297.63, "imp": 0}}, "300249": {"Brasil": {"exp": 321440.0, "imp": 1637127.54}, "Dinamarca": {"exp": 0, "imp": 39430.82}, "España": {"exp": 0, "imp": 6701.0}, "Alemania": {"exp": 0, "imp": 1647.06}, "Estados Unidos": {"exp": 0, "imp": 240322.1}, "China": {"exp": 0, "imp": 126.06}, "Italia": {"exp": 0, "imp": 753.0}, "Ghana": {"exp": 4480.0, "imp": 0}}, "300259": {"Chequia": {"exp": 0, "imp": 626.01}, "Francia": {"exp": 0, "imp": 20201.84}, "Italia": {"exp": 0, "imp": 994.88}, "Argentina": {"exp": 0, "imp": 6497.07}, "China": {"exp": 0, "imp": 7928.38}}, "300670": {"Malasia": {"exp": 0, "imp": 32810.42}, "Dinamarca": {"exp": 0, "imp": 3950.02}, "Países Bajos": {"exp": 0, "imp": 7656.15}, "Reino Unido": {"exp": 0, "imp": 20291.17}, "Turquía": {"exp": 0, "imp": 11786.94}, "India": {"exp": 0, "imp": 33149.6}, "Italia": {"exp": 0, "imp": 4508.0}, "España": {"exp": 0, "imp": 143294.47}, "Alemania": {"exp": 0, "imp": 12860.24}, "Estados Unidos": {"exp": 0, "imp": 5531.69}, "Argentina": {"exp": 0, "imp": 405.14}, "China": {"exp": 0, "imp": 37165.11}, "Brasil": {"exp": 0, "imp": 311.12}}, "300310": {"Bangladesh": {"exp": 0, "imp": 2.06}, "Rep. Dominicana": {"exp": 0, "imp": 19.35}, "Reino Unido": {"exp": 0, "imp": 1.19}, "Chile": {"exp": 0, "imp": 71.13}, "Países Bajos": {"exp": 0, "imp": 4100.0}, "China": {"exp": 0, "imp": 203645.57}}, "300691": {"Lituania": {"exp": 0, "imp": 11064.0}, "Irlanda": {"exp": 0, "imp": 2847.0}, "Rep. Dominicana": {"exp": 0, "imp": 10204.37}, "Francia": {"exp": 0, "imp": 361071.43}, "Alemania": {"exp": 0, "imp": 20137.0}, "Estados Unidos": {"exp": 0, "imp": 450951.26}, "Argentina": {"exp": 0, "imp": 15.22}, "Brasil": {"exp": 0, "imp": 7185.83}, "Italia": {"exp": 0, "imp": 53760.0}}, "300214": {"Reino Unido": {"exp": 0, "imp": 10626.32}, "Estados Unidos": {"exp": 0, "imp": 31046.71}, "Argentina": {"exp": 0, "imp": 877634.03}, "Alemania": {"exp": 0, "imp": 305.0}, "Francia": {"exp": 0, "imp": 920.0}}, "300339": {"México": {"exp": 0, "imp": 3614.0}, "India": {"exp": 0, "imp": 13080.0}}, "300650": {"Dinamarca": {"exp": 0, "imp": 3200.0}}}